Workbook

Sheet Бюджет 2026
B2: Доходы и расходы
B4: Продажи
C5: Январь 2024 | D5: Февраль 2024 | E5: Март 2024 | F5: Апрель 2024 | G5: Май 2024 | H5: Июнь 2024 | I5: Июль 2024 | J5: Август 2024 | K5: Сентябрь 2024 | L5: Октябрь 2024 | M5: Ноябрь 2024 | N5: Декабрь 2024 | O5: 2024 | P5: 2025 | Q5: % | R5: =P5 -> 2025 | S5: бюджет 2026 | T5: % | U5: Комментарий | V5: Ответсвенный
B6: Выручка от продаж разработки | C6: 1620120 | D6: 2444220 | E6: 2124600 | F6: 2080780 | G6: 2503840 | H6: 1851790 | I6: 2011800 | J6: 2391230 | K6: 3486230 | L6: 3523630 | M6: 3127680 | N6: 3307890 | O6: 32808910 | P6: 35069180 | Q6: =(P6-O6)/O6 -> 0.068891956 | R6: =P6 -> 35069180 | S6: =P6-P6*0.05+8000000+6000000 -> 47315721 | T6: =(S6-R6)/R6 -> 0.34921093 | U6: пункты 1a,1d, 2 роста прибыли | V6: Макшанова Л.М.
B7: Выручка сервера | C7: 5000 | D7: 5000 | E7: 5000 | F7: 5000 | G7: 5000 | H7: 5000 | I7: 5000 | J7: 5000 | K7: 5000 | L7: 5000 | M7: 5000 | N7: 5000 | O7: 60000 | P7: 215000 | Q7: =(P7-O7)/O7 -> 2.5833333 | R7: =P7 -> 215000 | S7: 400000 | T7: =(S7-R7)/R7 -> 0.86046512 | U7: Поднятие цен + 10 аренд | V7: Макшанова Л.М.
B8: Выручка коробки | C8: 0 | D8: 0 | E8: 0 | F8: 104700 | G8: 0 | H8: 0 | I8: 88128 | J8: 134280 | K8: 44064 | L8: 12000 | M8: 0 | N8: 44064 | O8: 1624218 | P8: 1749780 | Q8: =(P8-O8)/O8 -> 0.077306125 | R8: =P8 -> 1749780 | S8: 2500000 | T8: =(S8-R8)/R8 -> 0.42875104 | U8: Рост из за отсутствия НДС | V8: Макшанова Л.М.
B9: Выручка поддержка | C9: 169700 | D9: 183020 | E9: 189300 | F9: 223790 | G9: 82370 | H9: 112500 | I9: 99200 | J9: 102500 | K9: 110000 | L9: 102500 | M9: 113750 | N9: 83410 | O9: 1572040 | P9: 2371080 | Q9: =(P9-O9)/O9 -> 0.50828223 | R9: =P9 -> 2371080 | S9: 3500000 | T9: =(S9-R9)/R9 -> 0.47612059 | V9: Макшанова Л.М.
B10: Выручка продукты | P10: 500000 | R10: =P10 -> 500000 | S10: 3000000 | T10: =(S10-R10)/R10 -> 5 | U10: пункт 1d роста прибыли | V10: Макшанова Л.М.
B11: Итого выручка: | C11: 2420620 | D11: 3172240 | E11: 2998900 | F11: 3264470 | G11: 2591210 | H11: 1969290 | I11: 2204128 | J11: 2716010 | K11: 3826646 | L11: 3912080 | M11: 3293406 | N11: 3688168 | O11: 36057168 | P11: 39896240 | Q11: =(P11-O11)/O11 -> 0.10647181 | R11: =P11 -> 39896240 | S11: =S6+S7+S8+S9+S10 -> 56715721 | T11: =(S11-R11)/R11 -> 0.42158061
R12: =P12
B13: Себестоимость | R13: =P13
C14: Январь 2024 | D14: Февраль 2024 | E14: Март 2024 | F14: Апрель 2024 | G14: Май 2024 | H14: Июнь 2024 | I14: Июль 2024 | J14: Август 2024 | K14: Сентябрь 2024 | L14: Октябрь 2024 | M14: Ноябрь 2024 | N14: Декабрь 2024 | O14: 2024 | P14: 2025 | R14: =P14 -> 2025 | S14: бюджет 2026
B15: Себестоимость от продаж | C15: 658142.69 | D15: 838233.76 | E15: 784464.24 | F15: 737684.19 | G15: 926060 | H15: 696980.01 | I15: 785160.01 | J15: 850099.99 | K15: 1227780 | L15: 1280520 | M15: 966659.99 | N15: 1104560 | O15: 11245609 | P15: 11159397 | Q15: =(P15-O15)/O15 -> -0.0076663103 | R15: =P15 -> 11159397 | S15: =P15*(1.5) -> 16739095 | T15: =(S15-R15)/R15 -> 0.5 | V15: Сысоев В.С.
B16: Себестоимость коробки | C16: 0 | D16: 0 | E16: 0 | F16: 47154.67 | G16: 0 | H16: 0 | I16: 57288 | J16: 93996 | K16: 28644 | L16: 5400 | M16: 0 | N16: 28644 | O16: 949980.83 | P16: 1041424 | Q16: =(P16-O16)/O16 -> 0.096257911 | R16: =P16 -> 1041424 | S16: =S8/2 -> 1250000 | T16: =(S16-R16)/R16 -> 0.20027962 | V16: Макшанова Л.М.
B17: Итого себестоимость: | C17: 908295.97 | D17: 916995.45 | E17: 858797.63 | F17: 982350.67 | G17: 926060 | H17: 696980.01 | I17: 842448.01 | J17: 1008756.2 | K17: 1362459.1 | L17: 1427273 | M17: 991739.99 | N17: 1269834 | O17: 12191990 | P17: 12192901 | Q17: =(P17-O17)/O17 -> 7.4708066e-05 | R17: =P17 -> 12192901 | S17: =S15+S16 -> 17989095 | T17: =(S17-R17)/R17 -> 0.47537452
B18: Итого прибыль: | C18: 1512324 | D18: 2255244.5 | E18: 2140102.4 | F18: 2282119.3 | G18: 1665150 | H18: 1272310 | I18: 1361680 | J18: 1707253.8 | K18: 2464186.9 | L18: 2484807 | M18: 2301666 | N18: 2418334 | O18: 23865178 | P18: 27703339 | Q18: =(P18-O18)/O18 -> 0.16082684 | R18: =P18 -> 27703339 | S18: =S11-S17 -> 38726626 | T18: =(S18-R18)/R18 -> 0.39790462
B19: Рентабельность: | C19: 0.62476722 | D19: 0.71093125 | E19: 0.71362912 | F19: 0.69907805 | G19: 0.64261484 | H19: 0.64607548 | I19: 0.61778626 | J19: 0.62858893 | K19: 0.64395475 | L19: 0.63516262 | M19: 0.69887102 | N19: 0.65570062 | O19: 0.66187056 | P19: 0.69438471 | Q19: =(P19-O19)/O19 -> 0.049124639 | R19: =P19 -> 0.69438471 | S19: =S18/S11 -> 0.68281995 | T19: =(S19-R19)/R19 -> -0.016654692
R20: =P20
B21: Себестоимость прочая | R21: =P21
C22: Январь 2024 | D22: Февраль 2024 | E22: Март 2024 | F22: Апрель 2024 | G22: Май 2024 | H22: Июнь 2024 | I22: Июль 2024 | J22: Август 2024 | K22: Сентябрь 2024 | L22: Октябрь 2024 | M22: Ноябрь 2024 | N22: Декабрь 2024 | O22: 2024 | P22: 2025 | R22: =P22 -> 2025 | S22: бюджет 2026
B23: Простой | C23: 396200 | D23: 468740 | E23: 267100 | F23: 241360 | G23: 171180 | H23: 165000 | I23: 162590.1 | J23: 120000 | K23: 120000 | L23: 126800 | M23: 120000 | N23: 120000 | O23: 2478970.1 | P23: 1782145 | Q23: =(P23-O23)/O23 -> -0.28109461 | R23: =P23 -> 1782145 | S23: 1000000 | T23: =(S23-R23)/R23 -> -0.43887842 | V23: Сысоев В.С.
B24: Оплата попадосов | C24: 283900 | D24: 219510 | E24: 174300 | F24: 287200 | G24: 158450 | H24: 66100 | I24: 39200 | J24: 17400 | K24: 26500 | L24: 29900 | M24: 11200 | N24: 34900 | O24: 1348560 | P24: 946780 | Q24: =(P24-O24)/O24 -> -0.29793261 | R24: =P24 -> 946780 | S24: 500000 | T24: =(S24-R24)/R24 -> -0.47189421 | V24: Сысоев В.С.
B25: Выплата заработной платы разработка | C25: 32730 | D25: 31500 | E25: 55000 | F25: 116000 | G25: 66300 | H25: 73100 | I25: 255801.38 | J25: 155414 | K25: 152314 | L25: 166961.45 | M25: 137324.08 | N25: 159897 | O25: 1402341.9 | P25: 3492482.9 | Q25: =(P25-O25)/O25 -> 1.4904646 | R25: =P25 -> 3492482.9 | S25: 3000000 | T25: =(S25-R25)/R25 -> -0.14101226 | V25: Сысоев В.С.
B26: Оплата аналитики | C26: 143940 | D26: 169800 | E26: 168620 | F26: 172340 | G26: 192320 | H26: 136840 | I26: 140400 | J26: 176520 | K26: 262480 | L26: 259980 | M26: 202300 | N26: 224160 | O26: 2249700 | P26: 2162440 | Q26: =(P26-O26)/O26 -> -0.038787394 | R26: =P26 -> 2162440 | S26: 3000000 | T26: =(S26-R26)/R26 -> 0.38732173 | V26: Сысоев В.С.
B27: Откат ментам | C27: 107760 | D27: 197150 | E27: 200460 | F27: 213747 | G27: 146260 | H27: 82850 | I27: 89350 | J27: 162100 | K27: 285800 | L27: 287700 | M27: 260820 | N27: 281500 | O27: 2315497 | P27: 2597759 | Q27: =(P27-O27)/O27 -> 0.12190126 | R27: =P27 -> 2597759 | S27: 4000000 | T27: =(S27-R27)/R27 -> 0.53978872 | V27: Павлова Д.И.
B28: Бонус отдела продаж | C28: 0 | D28: 0 | E28: 0 | F28: 0 | G28: 0 | H28: 18000 | I28: 1320 | J28: 0 | K28: 12750 | L28: 0 | M28: 0 | N28: 0 | O28: 32070 | P28: 63343 | Q28: =(P28-O28)/O28 -> 0.97514811 | R28: =P28 -> 63343 | S28: 400000 | T28: =(S28-R28)/R28 -> 5.3148256 | V28: Макшанова Л.М.
B29: Итого Себестоимость прочая: | C29: 964530 | D29: 1086700 | E29: 865480 | F29: 1030647 | G29: 734510 | H29: 541890 | I29: 688661.48 | J29: 631434 | K29: 859844 | L29: 871341.45 | M29: 731644.08 | N29: 820 457,00 | O29: 9827139 | P29: 11044950 | Q29: =(P29-O29)/O29 -> 0.12392324 | R29: =P29 -> 11044950 | S29: =S28+S27+S26+S25+S24+S23 -> 11900000 | T29: =(S29-R29)/R29 -> 0.077415482
B30: Итого прибыль: | C30: 547 794,03 | D30: 1 168 544,55 | E30: 1 274 622,37 | F30: 1 251 472,33 | G30: 930 640,00 | H30: 730 419,99 | I30: 673 018,51 | J30: 1 075 819,83 | K30: 1 604 342,85 | L30: 1 613 465,55 | M30: 1 570 021,93 | N30: 1 597 877,03 | O30: 14038039 | P30: 16658389 | Q30: =(P30-O30)/O30 -> 0.18666071 | R30: =P30 -> 16658389 | S30: =S18-S29 -> 26826626 | T30: =(S30-R30)/R30 -> 0.61039734
B31: Рентабельность: | C31: 23% | D31: 37% | E31: 43% | F31: 38% | G31: 36% | H31: 37% | I31: 31% | J31: 40% | K31: 42% | L31: 41% | M31: 48% | N31: 43% | O31: 0.39 | P31: 0.42 | Q31: =(P31-O31)/O31 -> 0.076923077 | R31: =P31 -> 0.42 | S31: =S30/S11 -> 0.47300158 | T31: =(S31-R31)/R31 -> 0.12619424
R32: =P32
B33: Операционные расходы | R33: =P33
C34: Январь 2024 | D34: Февраль 2024 | E34: Март 2024 | F34: Апрель 2024 | G34: Май 2024 | H34: Июнь 2024 | I34: Июль 2024 | J34: Август 2024 | K34: Сентябрь 2024 | L34: Октябрь 2024 | M34: Ноябрь 2024 | N34: Декабрь 2024 | O34: 2024 | P34: 2025 | R34: =P34 -> 2025 | S34: бюджет 2026
B35: Выплата заработной платы(Операционные) | C35: 130 000,00 | D35: 130 000,00 | E35: 130 000,00 | F35: 130 000,00 | G35: 130 000,00 | H35: 130 000,00 | I35: 130 000,00 | J35: 130 000,00 | K35: 130 000,00 | L35: 130 000,00 | M35: 130 000,00 | N35: 130 000,00 | O35: 1560000 | P35: 1560000 | Q35: =(P35-O35)/O35 -> 0 | R35: =P35 -> 1560000 | S35: =P35*1.2 -> 1872000 | T35: =(S35-R35)/R35 -> 0.2 | U35: ростим зп | V35: Львов С.А.
B36: Итого Операционные расходы: | C36: 130 000,00 | D36: 130 000,00 | E36: 130 000,00 | F36: 130 000,00 | G36: 130 000,00 | H36: 130 000,00 | I36: 130 000,00 | J36: 130 000,00 | K36: 130 000,00 | L36: 130 000,00 | M36: 130 000,00 | N36: 130 000,00 | O36: 1560000 | P36: 1560000 | Q36: =(P36-O36)/O36 -> 0 | R36: =P36 -> 1560000 | S36: =P36 -> 1560000 | T36: =(S36-R36)/R36 -> 0
B37: Итого прибыль: | C37: 417 794,03 | D37: 1 038 544,55 | E37: 1 144 622,37 | F37: 1 121 472,33 | G37: 800 640,00 | H37: 600 419,99 | I37: 543 018,51 | J37: 945 819,83 | K37: 1 474 342,85 | L37: 1 483 465,55 | M37: 1 440 021,93 | N37: 1 467 877,03 | O37: 12478039 | P37: 15098389 | Q37: =(P37-O37)/O37 -> 0.20999696 | R37: =P37 -> 15098389 | S37: =S30-S36 -> 25266626 | T37: =(S37-R37)/R37 -> 0.67346498
B38: Рентабельность: | C38: 17% | D38: 33% | E38: 38% | F38: 34% | G38: 31% | H38: 30% | I38: 25% | J38: 35% | K38: 39% | L38: 38% | M38: 44% | N38: 40% | O38: 0.35 | P38: 0.38 | Q38: =(P38-O38)/O38 -> 0.085714286 | R38: =P38 -> 0.38 | S38: =S37/S11 -> 0.44549598 | T38: =(S38-R38)/R38 -> 0.17235784
R39: =P39
B40: Коммерческие расходы | R40: =P40
C41: Январь 2024 | D41: Февраль 2024 | E41: Март 2024 | F41: Апрель 2024 | G41: Май 2024 | H41: Июнь 2024 | I41: Июль 2024 | J41: Август 2024 | K41: Сентябрь 2024 | L41: Октябрь 2024 | M41: Ноябрь 2024 | N41: Декабрь 2024 | O41: 2024 | P41: 2025 | R41: =P41 -> 2025 | S41: бюджет 2026
B42: Выплата заработной платы(Развитие) | C42: 67 530,00 | D42: 113 330,00 | E42: 83000 | F42: 114 800,00 | G42: 157 400,00 | H42: 125 000,00 | I42: 79 350,00 | J42: 229 000,00 | K42: 265 000,00 | L42: 230 378,67 | M42: 220 750,00 | N42: 351 431,45 | O42: 2036970.1 | P42: 3842662.5 | Q42: =(P42-O42)/O42 -> 0.88645993 | R42: =P42 -> 3842662.5 | S42: =3840000 -> 3840000 | T42: =(S42-R42)/R42 -> -0.00069288416 | U42: Комер дир + 2 ОП | V42: Макшанова Л.М.
B43: Маркетинг | C43: 0 | D43: 0 | E43: 0 | F43: 0 | G43: 0 | H43: 0 | I43: 0 | J43: 0 | K43: 0 | L43: 0 | M43: 10 000,00 | N43: 0 | O43: 10000 | P43: 2449351 | Q43: =(P43-O43)/O43 -> 243.9351 | R43: =P43 -> 2449351 | S43: 1000000 | T43: =(S43-R43)/R43 -> -0.59172858 | U43: Бюджет на маркетинг + сео | V43: Львов С.А.
B44: RND | C44: 0 | D44: 0 | E44: 0 | F44: 0 | G44: 0 | H44: 0 | I44: 0 | J44: 0 | K44: 0 | L44: 0 | M44: 11 000,00 | N44: 1 | R44: =P44 | S44: 1000000 | U44: Добавлен бюджет на RND | V44: Львов С.А.
B45: Итого Коммерческие расходы: | C45: 67 530,00 | D45: 113 330,00 | E45: 83000 | F45: 114 800,00 | G45: 157 400,00 | H45: 125 000,00 | I45: 79 350,00 | J45: 229 000,00 | K45: 265 000,00 | L45: 230 378,67 | M45: 230 750,00 | N45: 351 431,45 | O45: 2046970.1 | P45: 6292013.5 | Q45: =(P45-O45)/O45 -> 2.073818 | R45: =P45 -> 6292013.5 | S45: =S42+S43+S44 -> 5840000 | T45: =(S45-R45)/R45 -> -0.071839248
B46: Итого прибыль: | C46: 350 264,03 | D46: 925 214,55 | E46: 1 061 622,37 | F46: 1 006 672,33 | G46: 643 240,00 | H46: 475 419,99 | I46: 463 668,51 | J46: 716 819,83 | K46: 1 209 342,85 | L46: 1 253 086,88 | M46: 1 209 271,93 | N46: 1 116 445,58 | O46: 10431069 | P46: 8806375.7 | Q46: =(P46-O46)/O46 -> -0.15575519 | R46: =P46 -> 8806375.7 | S46: =S37-S45 -> 19426626 | T46: =(S46-R46)/R46 -> 1.2059728
B47: Рентабельность: | C47: 14% | D47: 29% | E47: 35% | F47: 31% | G47: 25% | H47: 24% | I47: 21% | J47: 26% | K47: 32% | L47: 32% | M47: 37% | N47: 30% | O47: 0.29 | P47: 0.22 | Q47: =(P47-O47)/O47 -> -0.24137931 | R47: =P47 -> 0.22 | S47: =S46/S11 -> 0.34252629 | T47: =(S47-R47)/R47 -> 0.5569377
R48: =P48
B49: Постоянные расходы | R49: =P49
C50: Январь 2024 | D50: Февраль 2024 | E50: Март 2024 | F50: Апрель 2024 | G50: Май 2024 | H50: Июнь 2024 | I50: Июль 2024 | J50: Август 2024 | K50: Сентябрь 2024 | L50: Октябрь 2024 | M50: Ноябрь 2024 | N50: Декабрь 2024 | O50: 2024 | P50: 2025 | R50: =P50 -> 2025 | S50: бюджет 2026
B51: Налоги | C51: 402 000,00 | D51: 402 000,00 | E51: 402 000,00 | F51: 330 000,00 | G51: 330 000,00 | H51: 330 000,00 | I51: 330 000,00 | J51: 75 000,00 | K51: 100 000,00 | L51: 100 000,00 | M51: 100 000,00 | N51: 100 000,00 | O51: 1501000 | P51: 1489080 | Q51: =(P51-O51)/O51 -> -0.0079413724 | R51: =P51 -> 1489080 | S51: =S11*0.07 -> 3970100.5 | T51: =(S51-R51)/R51 -> 1.6661432 | U51: Сокращение налогово до 2% | V51: Павлова Д.И.
B52: Аренда серверов | C52: 4 075,00 | D52: 4 075,00 | E52: 4 075,00 | F52: 4 075,00 | G52: 4 075,00 | H52: 4 075,00 | I52: 4 075,00 | J52: 4 075,00 | K52: 4 075,00 | L52: 4 075,00 | M52: 4 075,00 | N52: 4 075,00 | O52: 48900 | P52: 62442.8 | Q52: =(P52-O52)/O52 -> 0.27694888 | R52: =P52 -> 62442.8 | S52: 70000 | T52: =(S52-R52)/R52 -> 0.12102596 | U52: оптимизация затрат | V52: Гатих П.С.
B53: Транспорт | C53: 4 297,79 | D53: 569,50 | E53: 530,00 | F53: 0 | G53: 2 000,00 | H53: 4 820,00 | I53: 3 252,89 | J53: 2 246,51 | K53: 3 000,00 | L53: 3 634,00 | M53: 2 510,00 | N53: 0 | O53: 26860.69 | P53: 46203 | Q53: =(P53-O53)/O53 -> 0.72009729 | R53: =P53 -> 46203 | S53: 50000 | T53: =(S53-R53)/R53 -> 0.082180811 | U53: Оптимизация затрат | V53: Павлова Д.И.
B54: Аренда офиса | C54: 115 572,80 | D54: 115 572,80 | E54: 115 572,80 | F54: 78 106,41 | G54: 81 043,83 | H54: 81 043,83 | I54: 81 043,83 | J54: 81 043,83 | K54: 81 043,83 | L54: 81 043,83 | M54: 81 043,83 | N54: 81 043,83 | O54: 1073175.4 | P54: 888553.19 | Q54: =(P54-O54)/O54 -> -0.17203362 | R54: =P54 -> 888553.19 | S54: 1000000 | T54: =(S54-R54)/R54 -> 0.12542503 | V54: Павлова Д.И.
B55: Связь | C55: 7 803,23 | D55: 16 900,00 | E55: 16 900,00 | F55: 16 900,00 | G55: 19 000,00 | H55: 17400 | I55: 6 900,00 | J55: 16 900,00 | K55: 16 900,00 | L55: 13 900,00 | M55: 15 400,00 | N55: 16 900,00 | O55: 181803.23 | P55: 232100 | Q55: =(P55-O55)/O55 -> 0.27665499 | R55: =P55 -> 232100 | S55: 150000 | T55: =(S55-R55)/R55 -> -0.35372684 | U55: снижение трафика, собственная линия связи | V55: Гатих П.С.
B56: Офис | C56: 55 287,00 | D56: 95 419,53 | E56: 103 734,00 | F56: 86 304,00 | G56: 100 641,00 | H56: 72 122,00 | I56: 73 427,44 | J56: 26 652,00 | K56: 85 686,00 | L56: 62 027,00 | M56: 53 657,00 | N56: 132 652,10 | O56: 947609.07 | P56: 1076764.5 | Q56: =(P56-O56)/O56 -> 0.13629608 | R56: =P56 -> 1076764.5 | S56: 500000 | T56: =(S56-R56)/R56 -> -0.5356459 | U56: Контроль затрат (не более 41 600 в мес.) | V56: Гатих П.С.
B57: Выплата заработной платы(Коммерческие) | C57: 360 000,00 | D57: 360 000,00 | E57: 360 000,00 | F57: 360 000,00 | G57: 360 000,00 | H57: 360 000,00 | I57: 360 000,00 | J57: 360 000,00 | K57: 360 000,00 | L57: 360 000,00 | M57: 360 000,00 | N57: 360 000,00 | O57: 4320000 | P57: 4246836 | Q57: =(P57-O57)/O57 -> -0.016936118 | R57: =P57 -> 4246836 | S57: 5000000 | T57: =(S57-R57)/R57 -> 0.1773471 | U57: ростим зп | V57: Львов С.А.
B58: Комисии | C58: 14 507,00 | D58: 18 313,50 | E58: 13 854,50 | F58: 11 662,50 | G58: 13 394,00 | H58: 9 758,71 | I58: 2 436,64 | J58: 13 133,43 | K58: 10 827,00 | L58: 12 883,15 | M58: 10 305,75 | N58: 29 163,90 | O58: 160240.08 | P58: 382603.73 | Q58: =(P58-O58)/O58 -> 1.3876906 | R58: =P58 -> 382603.73 | S58: 100000 | T58: =(S58-R58)/R58 -> -0.73863297 | U58: сокращаем комиссии | V58: Павлова Д.И.
B59: Обучение | C59: 0 | D59: 0 | E59: 0 | F59: 11 000,00 | G59: 0 | H59: 0 | I59: 500,00 | J59: 1 000,00 | K59: 0 | L59: 0 | M59: 14 800,00 | N59: 0 | O59: 28300 | P59: 43708 | Q59: =(P59-O59)/O59 -> 0.5444523 | R59: =P59 -> 43708 | S59: 100000 | T59: =(S59-R59)/R59 -> 1.2879107 | U59: Увеличиваем бюджет на обучение | V59: Львов С.А.
B60: Налоги ЗП | C60: 0 | D60: 0 | E60: 0 | F60: 0 | G60: 0 | H60: 0 | I60: 0 | J60: 285 000,00 | K60: 285 000,00 | L60: 285 000,00 | M60: 285 000,00 | N60: 285 000,00 | O60: 2925000 | P60: 3347287.2 | Q60: =(P60-O60)/O60 -> 0.14437169 | R60: =P60 -> 3347287.2 | S60: =S11*0.07 -> 3970100.5 | T60: =(S60-R60)/R60 -> 0.18606509 | U60: сокращаем налог на зп | V60: Павлова Д.И.
B61: Итого Постоянные расходы: | C61: 963 542,81 | D61: 1 012 850,31 | E61: 1 016 666,30 | F61: 898 047,94 | G61: 910 153,83 | H61: 879 219,53 | I61: 862 635,79 | J61: 865 050,78 | K61: 946 531,83 | L61: 922 563,00 | M61: 926 791,59 | N61: 1 008 834,84 | O61: 11212889 | P61: 11815578 | Q61: =(P61-O61)/O61 -> 0.053749735 | R61: =P61 -> 11815578 | S61: =SUM(S51:S60) -> 14910201 | T61: =(S61-R61)/R61 -> 0.26191038
B62: Итого прибыль: | C62: -613 278,78 | D62: -87 635,76 | E62: 44 956,07 | F62: 108 624,39 | G62: -266 913,83 | H62: -403 799,54 | I62: -398 967,28 | J62: -148 230,95 | K62: 262 811,02 | L62: 330 523,88 | M62: 282 480,34 | N62: 107 610,74 | O62: -781819.7 | P62: -3009202.6 | Q62: =(P62-O62)/O62 -> 2.8489726 | R62: =P62 -> -3009202.6 | S62: =S46-S61 -> 4516424.8 | T62: =(S62-R62)/R62 -> -2.500871
B63: Рентабельность: | C63: -25% | D63: -3% | E63: 1% | F63: 3% | G63: -10% | H63: -21% | I63: -18% | J63: -5% | K63: 7% | L63: 8% | M63: 9% | N63: 3% | O63: -0.02 | P63: -0.08 | Q63: =(P63-O63)/O63 -> 3 | R63: =P63 -> -0.08 | S63: =S62/S11 -> 0.079632678 | T63: =(S63-R63)/R63 -> -1.9954085
R64: =P64
B65: Справочно | R65: =P65
C66: Январь 2024 | D66: Февраль 2024 | E66: Март 2024 | F66: Апрель 2024 | G66: Май 2024 | H66: Июнь 2024 | I66: Июль 2024 | J66: Август 2024 | K66: Сентябрь 2024 | L66: Октябрь 2024 | M66: Ноябрь 2024 | N66: Декабрь 2024 | O66: 2024 | P66: 2025 | R66: =P66 -> 2025
B67: Количество закрытых часов | C67: 770,20 | D67: 1 075,80 | E67: 988,50 | F67: 980,40 | G67: 932,70 | H67: 683,20 | I67: 752,00 | J67: 893,40 | K67: 1 300,40 | L67: 1 314,90 | M67: 1 058,10 | N67: 1 118,10 | O67: 11867.7 | P67: 11860 | Q67: =(P67-O67)/O67 -> -0.00064881991 | R67: =P67 -> 11860 | S67: =S11/S69 -> 15754.367 | T67: =(S67-R67)/R67 -> 0.32836146
B68: Из них маркетинга | C68: 85,60 | D68: 363,60 | E68: 295,80 | F68: 229,00 | G68: 43,20 | H68: 31,30 | I68: 16,50 | J68: 91,60 | K68: 151,00 | L68: 108,20 | M68: 137,10 | N68: 74,90 | O68: 1627.8 | P68: 957.9 | Q68: =(P68-O68)/O68 -> -0.41153704 | R68: =P68 -> 957.9 | S68: =S67*0.1 -> 1575.4367 | T68: =(S68-R68)/R68 -> 0.64467762
B69: Средняя цена часа: | C69: 2 804,62 | D69: 2 773,95 | E69: 2 837,23 | F69: 2 708,98 | G69: 2 684,51 | H69: 2 710,47 | I69: 2 675,27 | J69: 2 676,55 | K69: 2 680,89 | L69: 2 679,77 | M69: 2 955,94 | N69: 2 958,49 | O69: 2764.56 | P69: 3017.22 | Q69: =(P69-O69)/O69 -> 0.091392482 | R69: =P69 -> 3017.22 | S69: 3600 | T69: =(S69-R69)/R69 -> 0.19315131
B70: Средняя себестоимость часа: | C70: 2 220,66 | D70: 1 777,45 | E70: 1 648,59 | F70: 1 754,46 | G70: 1 736,23 | H70: 1 731,00 | I70: 1 893,91 | J70: 1 600,94 | K70: 1 563,08 | L70: 1 597,54 | M70: 1 551,30 | N70: 1 684,39 | O70: 682.08 | P70: 770.64 | Q70: =(P70-O70)/O70 -> 0.12983814 | R70: =P70 -> 770.64 | S70: =S15/S67 -> 1062.5051 | T70: =(S70-R70)/R70 -> 0.3787308
B71: Рентабельность часа: | C71: 583,96 | D71: 996,50 | E71: 1 188,64 | F71: 954,51 | G71: 948,27 | H71: 979,46 | I71: 781,35 | J71: 1 075,61 | K71: 1 117,81 | L71: 1 082,23 | M71: 1 404,64 | N71: 1 274,11 | O71: 2082.47 | P71: 2246.58 | Q71: =(P71-O71)/O71 -> 0.078805457 | R71: =P71 -> 2246.58 | S71: =S69-S70 -> 2537.4949 | T71: =(S71-R71)/R71 -> 0.12949234
B72: Доходность часа: | C72: 21% | D72: 36% | E72: 42% | F72: 35% | G72: 35% | H72: 36% | I72: 29% | J72: 40% | K72: 42% | L72: 40% | M72: 48% | N72: 43% | O72: 0.75 | P72: 0.74 | Q72: =(P72-O72)/O72 -> -0.013333333 | R72: =P72 -> 0.74 | S72: =S71/S69 -> 0.70485969 | T72: =(S72-R72)/R72 -> -0.047486901

Sheet Помесячно Заполнить ответственн
A1: 0 | B1: Ответственный | C1: Месяц | D1: Квартал | E1: План | F1: Факт | G1: Комментарий
A2: 01.1.Выручка от продаж разработки | B2: Макшанова Л.М. | C2: 01.Январь | D2: 1 | E2: ='Макшанова'!H37 -> 0
A3: 01.2.Выручка от продаж разработки | B3: Сысоев В.С. | C3: 01.Январь | D3: 1 | E3: 1927665 | F3: 1927665 | H3: по плану видно что будет в районе 2 млн
A4: 02.1.Выручка сервера | B4: Макшанова Л.М. | C4: 01.Январь | D4: 1 | E4: ='Макшанова'!H39 -> 20000 | F4: 20000
A5: 03.1.Выручка коробки | B5: Макшанова Л.М. | C5: 01.Январь | D5: 1 | E5: ='Макшанова'!H43 -> 71800 | F5: 71800
A6: 04.1.Выручка поддержка | B6: Макшанова Л.М. | C6: 01.Январь | D6: 1 | E6: ='Макшанова'!H57 -> 83400 | F6: 83400
A7: 05.1.Выручка продукты | B7: Макшанова Л.М. | C7: 01.Январь | D7: 1 | E7: ='Макшанова'!H79 -> 53100 | F7: 53100
A8: 06.Себестоимость от продаж | B8: Макшанова Л.М. | C8: 01.Январь | D8: 1 | E8: =J8*0.35*(-1) -> -674682.75 | F8: -554535.54 | J8: =E3+E2 -> 1927665
A9: 07.Себестоимость коробки | B9: Макшанова Л.М. | C9: 01.Январь | D9: 1 | E9: =E5*0.5*(-1) -> -35900 | F9: -34865
A10: 08.Простой | B10: Макшанова Л.М. | C10: 01.Январь | D10: 1 | E10: -250000 | F10: -408840
A11: 09.Оплата попадосов | B11: Сысоев В.С. | C11: 01.Январь | D11: 1 | E11: -50000 | F11: -50000
A12: 10.Выплата заработной платы разработка | B12: Сысоев В.С. | C12: 01.Январь | D12: 1 | E12: -119740 | F12: -119740 | H12: в концепции что это оплата за работу специалиста по поддержке посчитано по средней ставке поддержки 3200 и плана 100 тысяч из расчета что 100% идет в ЗП по средней ствке аналитики 1350
A13: 11.Оплата аналитики | B13: Сысоев В.С. | C13: 01.Январь | D13: 1 | E13: -111020 | F13: -111020 | H13: цена часа 3200 | J13: =0+J8 -> 1927665
A14: 12.Откат ментам | B14: Павлова Д.И. | C14: 01.Январь | D14: 1 | E14: -333333.33 | F14: -100340
A15: 13.Бонус отдела продаж | B15: Макшанова Л.М. | C15: 01.Январь | D15: 1 | E15: -20000 | F15: 0
A16: 14.Выплата заработной платы(Операционные) | B16: Львов С.А. | C16: 01.Январь | D16: 1 | E16: -130000 | F16: -130000
A17: 15.Выплата заработной платы(Развитие) | B17: Макшанова Л.М. | C17: 01.Январь | D17: 1 | E17: -320000 | F17: -212500
A18: 16.Маркетинг | B18: Львов С.А. | C18: 01.Январь | D18: 1 | E18: 0 | F18: 0
A19: 17.RND | B19: Львов С.А. | C19: 01.Январь | D19: 1 | E19: 0 | F19: 0
A20: 18.Налоги | B20: Павлова Д.И. | C20: 01.Январь | D20: 1 | E20: -300000 | F20: -150000
A21: 19.Аренда серверов | B21: Гатих П.С. | C21: 01.Январь | D21: 1 | E21: -5834 | F21: -5225
A22: 20.Транспорт | B22: Павлова Д.И. | C22: 01.Январь | D22: 1 | E22: -4100 | F22: 0
A23: 21.Аренда офиса | B23: Павлова Д.И. | C23: 01.Январь | D23: 1 | E23: -87000 | F23: -86536
A24: 22.Связь | B24: Гатих П.С. | C24: 01.Январь | D24: 1 | E24: -17000 | F24: -12333.61
A25: 23.Офис | B25: Гатих П.С. | C25: 01.Январь | D25: 1 | E25: -41660 | F25: -106803
... A27: 25.Комисии | B27: Павлова Д.И. | C27: 01.Январь | D27: 1 | E27: -8300 | F27: -23800
A28: 25.Обучение | B28: Львов С.А. | C28: 01.Январь | D28: 1 | F28: 0
A29: 26.Налоги ЗП | B29: Павлова Д.И. | C29: 01.Январь | D29: 1 | E29: -300000 | F29: -385000
A30: 19.Аренда серверов | B30: Гатих П.С. | C30: 02.Февраль | D30: 1 | E30: -5834 | F30: -5225
A31: 01.1.Выручка от продаж разработки | B31: Макшанова Л.М. | C31: 02.Февраль | D31: 1 | E31: ='Макшанова'!L37 -> 182820 | F31: 0
A32: 02.1.Выручка сервера | B32: Макшанова Л.М. | C32: 02.Февраль | D32: 1 | E32: ='Макшанова'!L39 -> 25600 | F32: 19200
A33: 03.1.Выручка коробки | B33: Макшанова Л.М. | C33: 02.Февраль | D33: 1 | E33: ='Макшанова'!L43 -> 221400 | F33: 0
A34: 04.1.Выручка поддержка | B34: Макшанова Л.М. | C34: 02.Февраль | D34: 1 | E34: ='Макшанова'!L57 -> 38000 | F34: 57600
A35: 05.1.Выручка продукты | B35: Макшанова Л.М. | C35: 02.Февраль | D35: 1 | E35: ='Макшанова'!L79 -> 123900 | F35: 0
A36: 06.Себестоимость от продаж | B36: Сысоев В.С. | C36: 02.Февраль | D36: 1 | E36: =(E57+E31)*0.35*(-1) -> -941787 | F36: -679260.02 | J36: =E31+E58 -> 890570
A37: 07.Себестоимость коробки | B37: Макшанова Л.М. | C37: 02.Февраль | D37: 1 | E37: =E33*0.5*(-1) -> -110700 | F37: 0
A38: 08.Простой | B38: Сысоев В.С. | C38: 02.Февраль | D38: 1 | E38: -150000 | F38: -185100
A39: 09.Оплата попадосов | B39: Сысоев В.С. | C39: 02.Февраль | D39: 1 | E39: -100000 | F39: -74100
A40: 10.Выплата заработной платы разработка | B40: Сысоев В.С. | C40: 02.Февраль | D40: 1 | E40: -42180 | F40: -119500 | H40: в концепции что это оплата за работу специалиста по поддержке посчитано по средней ставке поддержки 3200 и плана 100 тысяч из расчета что 100% идет в ЗП по средней ствке аналитики 1350
A41: 11.Оплата аналитики | B41: Сысоев В.С. | C41: 02.Февраль | D41: 1 | E41: =E57*200/3300*(-1) -> -152000 | F41: -137040 | H41: цена часа 3300 | J41: =0+J36 -> 890570
A42: 12.Откат ментам | B42: Павлова Д.И. | C42: 02.Февраль | D42: 1 | E42: -333333.33 | F42: -147150
A43: 13.Бонус отдела продаж | B43: Макшанова Л.М. | C43: 02.Февраль | D43: 1 | E43: -33333.333 | F43: 0
A44: 14.Выплата заработной платы(Операционные) | B44: Львов С.А. | C44: 02.Февраль | D44: 1 | E44: -130000 | F44: -130000
A45: 15.Выплата заработной платы(Развитие) | B45: Макшанова Л.М. | C45: 02.Февраль | D45: 1 | E45: -320000 | F45: -261850
A46: 16.Маркетинг | B46: Львов С.А. | C46: 02.Февраль | D46: 1 | E46: 0 | F46: 0
A47: 17.RND | B47: Львов С.А. | C47: 02.Февраль | D47: 1 | E47: 0 | F47: 0
A48: 18.Налоги | B48: Павлова Д.И. | C48: 02.Февраль | D48: 1 | E48: -300000 | F48: -170000
A49: 20.Транспорт | B49: Павлова Д.И. | C49: 02.Февраль | D49: 1 | E49: -4100 | F49: 0
A50: 21.Аренда офиса | B50: Павлова Д.И. | C50: 02.Февраль | D50: 1 | E50: -123000 | F50: -135307.42
A51: 22.Связь | B51: Гатих П.С. | C51: 02.Февраль | D51: 1 | E51: -17000 | F51: -24233
A52: 23.Офис | B52: Гатих П.С. | C52: 02.Февраль | D52: 1 | E52: -41660 | F52: -37016.81
A53: 24.Выплата заработной платы(Коммерческие) | B53: Львов С.А. | C53: 02.Февраль | D53: 1 | E53: -375000 | F53: -365000
A54: 25.Комисии | B54: Павлова Д.И. | C54: 02.Февраль | D54: 1 | E54: -23800 | F54: -25500
A55: 25.Обучение | B55: Львов С.А. | C55: 02.Февраль | D55: 1 | F55: 0
A56: 26.Налоги ЗП | B56: Павлова Д.И. | C56: 02.Февраль | D56: 1 | E56: -300000 | F56: -385000
A57: 01.2.Выручка от продаж разработки | B57: Сысоев В.С. | C57: 02.Февраль | D57: 1 | E57: 2508000 | F57: 2376135
A58: 01.1.Выручка от продаж разработки | B58: Макшанова Л.М. | C58: 03.Март | D58: 1 | E58: ='Макшанова'!O37 -> 707750 | F58: 4185030
A59: 02.1.Выручка сервера | B59: Макшанова Л.М. | C59: 03.Март | D59: 1 | E59: ='Макшанова'!O39 -> 32000 | F59: 24200
A60: 03.1.Выручка коробки | B60: Макшанова Л.М. | C60: 03.Март | D60: 1 | E60: ='Макшанова'!O43 -> 164000 | F60: 114000
A61: 04.1.Выручка поддержка | B61: Макшанова Л.М. | C61: 03.Март | D61: 1 | E61: ='Макшанова'!O57 -> 38000 | F61: 81000
A62: 05.1.Выручка продукты | B62: Макшанова Л.М. | C62: 03.Март | D62: 1 | E62: ='Макшанова'!O79 -> 223900
A63: 06.Себестоимость от продаж | B63: Сысоев В.С. | C63: 03.Март | D63: 1 | E63: =(E85+E58)*0.35*(-1) -> -1334112.5 | F63: -1175600 | J63: =E58+E85 -> 3811750
A64: 07.Себестоимость коробки | B64: Макшанова Л.М. | C64: 03.Март | D64: 1 | E64: =E60*0.5*(-1) -> -82000 | F64: -50000
A65: 08.Простой | B65: Сысоев В.С. | C65: 03.Март | D65: 1 | E65: -70000 | F65: -276120
A66: 09.Оплата попадосов | B66: Сысоев В.С. | C66: 03.Март | D66: 1 | E66: -50000 | F66: -66800
A67: 10.Выплата заработной платы разработка | B67: Сысоев В.С. | C67: 03.Март | D67: 1 | E67: -42180 | F67: -120720 | H67: в концепции что это оплата за работу специалиста по поддержке посчитано по средней ставке поддержки 3200 и плана 100 тысяч из расчета что 100% идет в ЗП по средней ствке аналитики 1350
A68: 11.Оплата аналитики | B68: Сысоев В.С. | C68: 03.Март | D68: 1 | E68: =E85*200/3300*(-1) -> -188121.21 | F68: -250440 | J68: =J63 -> 3811750
A69: 12.Откат ментам | B69: Павлова Д.И. | C69: 03.Март | D69: 1 | E69: -333333.33 | F69: -359050
A70: 13.Бонус отдела продаж | B70: Макшанова Л.М. | C70: 03.Март | D70: 1 | E70: -33333.333 | F70: -18500
A71: 14.Выплата заработной платы(Операционные) | B71: Львов С.А. | C71: 03.Март | D71: 1 | E71: -130000 | F71: -130000
A72: 15.Выплата заработной платы(Развитие) | B72: Макшанова Л.М. | C72: 03.Март | D72: 1 | E72: -320000 | F72: -230350
A73: 16.Маркетинг | B73: Львов С.А. | C73: 03.Март | D73: 1 | E73: 0 | F73: 0
A74: 17.RND | B74: Львов С.А. | C74: 03.Март | D74: 1 | E74: 0 | F74: 0
A75: 18.Налоги | B75: Павлова Д.И. | C75: 03.Март | D75: 1 | E75: -300000 | F75: -170000
A76: 19.Аренда серверов | B76: Гатих П.С. | C76: 03.Март | D76: 1 | E76: -5834 | F76: -5325
A77: 20.Транспорт | B77: Павлова Д.И. | C77: 03.Март | D77: 1 | E77: -4100 | F77: 0
A78: 21.Аренда офиса | B78: Павлова Д.И. | C78: 03.Март | D78: 1 | E78: -123000 | F78: -135307.42
A79: 22.Связь | B79: Гатих П.С. | C79: 03.Март | D79: 1 | E79: -17000 | F79: -15600
A80: 23.Офис | B80: Гатих П.С. | C80: 03.Март | D80: 1 | E80: -41660 | F80: -53287
... A82: 25.Комисии | B82: Павлова Д.И. | C82: 04.Апрель | D82: 1 | E82: -23800 | F82: -14325
A83: 25.Обучение | B83: Львов С.А. | C83: 03.Март | D83: 1 | F83: 0
A84: 26.Налоги ЗП | B84: Павлова Д.И. | C84: 03.Март | D84: 1 | E84: -300000 | F84: -405000
A85: 01.2.Выручка от продаж разработки | B85: Сысоев В.С. | C85: 03.Март | D85: 1 | E85: 3104000
A86: 01.1.Выручка от продаж разработки | B86: Макшанова Л.М. | C86: 04.Апрель | D86: 2 | E86: ='Макшанова'!R37 -> 608000 | F86: 31500
A87: 02.1.Выручка сервера | B87: Макшанова Л.М. | C87: 04.Апрель | D87: 2 | E87: ='Макшанова'!R39 -> 32000 | F87: 19200
A88: 03.1.Выручка коробки | B88: Макшанова Л.М. | C88: 04.Апрель | D88: 2 | E88: ='Макшанова'!R56 -> 100000 | F88: 14700
A89: 04.1.Выручка поддержка | B89: Макшанова Л.М. | C89: 04.Апрель | D89: 2 | E89: ='Макшанова'!R57 -> 38000 | F89: 54000
A90: 05.1.Выручка продукты | B90: Макшанова Л.М. | C90: 04.Апрель | D90: 2 | E90: ='Макшанова'!R79 -> 97650 | F90: 48657
A91: 06.Себестоимость от продаж | B91: Сысоев В.С. | C91: 04.Апрель | D91: 2 | E91: =(E113+E86)*0.35*(-1) -> -1310050 | F91: -1265804 | J91: =E86+E113 -> 3743000
A92: 07.Себестоимость коробки | B92: Макшанова Л.М. | C92: 04.Апрель | D92: 2 | E92: =E88*0.5*(-1) -> -50000 | F92: -7500
A93: 08.Простой | B93: Сысоев В.С. | C93: 04.Апрель | D93: 2 | E93: -70000 | F93: -72320
A94: 09.Оплата попадосов | B94: Сысоев В.С. | C94: 04.Апрель | D94: 2 | E94: -50000 | F94: -136400
A95: 10.Выплата заработной платы разработка | B95: Сысоев В.С. | C95: 04.Апрель | D95: 2 | E95: -42180 | F95: -275468 | H95: в концепции что это оплата за работу специалиста по поддержке посчитано по средней ставке поддержки 3200 и плана 100 тысяч из расчета что 100% идет в ЗП по средней ствке аналитики 1350
A96: 11.Оплата аналитики | B96: Сысоев В.С. | C96: 04.Апрель | D96: 2 | E96: =E113*200/3300*(-1) -> -190000 | F96: -265800 | J96: =J91 -> 3743000
A97: 12.Откат ментам | B97: Павлова Д.И. | C97: 04.Апрель | D97: 2 | E97: -333333.33 | F97: -391800
A98: 13.Бонус отдела продаж | B98: Макшанова Л.М. | C98: 04.Апрель | D98: 2 | E98: -33333.333 | F98: 0
A99: 14.Выплата заработной платы(Операционные) | B99: Львов С.А. | C99: 04.Апрель | D99: 2 | E99: -130000 | F99: -130000
A100: 15.Выплата заработной платы(Развитие) | B100: Макшанова Л.М. | C100: 04.Апрель | D100: 2 | E100: -320000 | F100: -305400
A101: 16.Маркетинг | B101: Львов С.А. | C101: 04.Апрель | D101: 2 | E101: 0 | F101: 0
A102: 17.RND | B102: Львов С.А. | C102: 04.Апрель | D102: 2 | E102: 0 | F102: 0
...

Sheet Поквартально
A35: ПОМЕСЯЧНО

Sheet Инфо20-06.Себестоимость от прод
A1: 0 | B1: Ответственный | C1: Месяц | D1: Квартал | E1: План | F1: Факт | G1: Комментарий
A2: 06.Себестоимость от продаж разработки | B2: Сысоев В.С. | C2: 05.Май | D2: 2 | E2: -928200 | F2: -1437760

Sheet Макшанова
B1: Продажи
H2: Январь 2024 | L2: Февраль 2024 | O2: Март 2024 | R2: Апрель 2024 | U2: Май 2024 | X2: Июнь 2024 | AA2: Июль 2024 | AD2: Август 2024 | AG2: Сентябрь 2024 | AJ2: Октябрь 2024 | AM2: Ноябрь 2024 | AP2: Декабрь 2024 | AS2: План ИТОГО | AT2: бюджет 2026 | AU2: Ответсвенный
C3: Договор | D3: Дата | E3: часы январь | F3: Ставка | G3: % повышения | H3: План | I3: Факт | J3: Комментарий | K3: часы февраль | L3: План | M3: Факт | N3: Комментарий | O3: План | P3: Факт | Q3: Комментарий | R3: План | S3: Факт | T3: Комментарий | U3: План | V3: Факт | W3: Комментарий | X3: План | Y3: Факт | Z3: Комментарий | AA3: План | AB3: Факт | AC3: Комментарий | AD3: План | AE3: Факт | AF3: Комментарий | AG3: План | AH3: Факт | AI3: Комментарий | AJ3: План | AK3: Факт | AL3: Комментарий | AM3: План | AN3: Факт | AO3: Комментарий | AP3: План | AQ3: Факт | AR3: Комментарий | AS3: План Итого
B4: Выручка от продаж разработки | H4: =H37 -> 0 | I4: 0 | J4: 0 | L4: 297 850,00 | M4: 0 | N4: 0 | O4: 814 650,00 | P4: 0 | Q4: 0 | R4: 986 200,00 | S4: 0 | T4: 0 | U4: 663 050,00 | V4: 0 | W4: 0 | X4: 759 992,00 | Y4: 0 | Z4: 0 | AA4: 629 000,00 | AB4: 0 | AC4: 0 | AD4: 896 934,00 | AE4: 0 | AF4: 0 | AG4: 782 750,00 | AH4: 0 | AI4: 0 | AJ4: 816 550,00 | AK4: 0 | AL4: 0 | AM4: 883 492,00 | AN4: 0 | AO4: 0 | AP4: 672 042,00 | AQ4: 0 | AS4: 8670400 | AT4: 47 315 721,00 | AU4: Макшанова Л.М.
A5: 1 | B5: X-COM | C5: - | D5: - | E5: 550 | F5: 3000 | G5: 0 | H5: =E5*F5 -> 1650000
A6: 2 | B6: АРТИС | C6: не нашла | D6: - | E6: 150 | F6: 2800 | G6: 20 (3360р)
A7: 3 | B7: Симон Электрик | C7: 1С/0111/2023 | D7: 45231 | E7: 30 | F7: 3700 | G7: 10,81 (4100р)
A8: 4 | B8: Кертинг РУС | C8: 0808/2024 | D8: 46000 | E8: 57 | F8: 3600 | G8: -
A9: 5 | B9: Доза | C9: 25/07/2024-1 | D9: 45498 | E9: 40 | F9: 3000 | G9: 20 (3600)
A10: 6 | B10: Металл Сервис | C10: 28/05/2025-1 | D10: 45805 | E10: 5 | F10: 3570 | G10: 5 (3570)
A11: 7 | B11: Хольц-Хаус | F11: 3300 | G11: -
B12: Хольц-Хаус Урал | C12: 02/06/2025-3 | D12: 45810 | E12: 1 | F12: 3300 | G12: -
B13: Хольц Хаус Москва | C13: 02/06/2025-5 | D13: 45810 | E13: 1 | F13: 3300 | G13: -
B14: Хольц Хаус Северо-Запад | C14: 02/06/2025-6 | D14: 45810 | E14: 1 | F14: 3300 | G14: -
B15: Хольц Эстейт | C15: 02/06/2025-2 | D15: 45810 | E15: 1 | F15: 3300 | G15: -
B16: Хольц Солюшенс | C16: 02/06/2025-4 (не подписан) | D16: 45810 | E16: 1 | F16: 3300 | G16: -
B17: Хольц Констракшн | C17: 02/06/2025-1 | D17: 45810 | E17: 1 | F17: 3300 | G17: -
A18: 8 | B18: РЭК | E18: 20 | F18: 4140 | G18: 15 (4140)
A19: 9 | B19: СТГ ГВАРД | E19: 0 | F19: 4140 | G19: 15 (4140)
A20: 10 | B20: АО «НФ АК ПРАКТИК» | E20: 0 | F20: 3600 | G20: -
A21: 11 | B21: Соглашение | E21: 40 | F21: 3800 | G21: 5,5 (3800)
A22: 12 | B22: ГК Керамогранит | E22: 10 | F22: 3000 | G22: 20 (3600)
A23: 13 | B23: Армтек | E23: 12.5 | F23: 3300 | G23: -
A24: 14 | B24: У-УАЗ | F24: 2700
A25: 15 | B25: Телеинвест | E25: 30 | F25: 3600 | G25: -
A26: 16 | B26: Гагава Ресторантс | F26: 3300 | G26: не работаем | I26: 0
A27: 17 | B27: АО «Атомспецтранс» | G27: не работаем
A28: 18 | B28: МикроЭм Технологии | G28: не работаем
B29: НОВЫЕ Разработка | AS29: 12000000
A30: 19 | B30: ИП Колосов | E30: 23 | F30: 3990 | G30: новые | L30: =3950*18 -> 71100 | AS30: =I30+L30+O30+R30+U30+X30+AA30+AD30+AG30+AJ30+AM30+AP30 -> 71100 | AU30: Макшанова Л.М.
B31: Примум Мебель | E31: 18 | F31: 3990 | L31: =E31*F31 -> 71820 | AS31: =I31+L31+O31+R31+U31+X31+AA31+AD31+AG31+AJ31+AM31+AP31 -> 71820
A32: 20 | B32: Алимп | E32: 5 | F32: 3990 | G32: новые | L32: =E32*F32 -> 19950 | AS32: =I32+L32+O32+R32+U32+X32+AA32+AD32+AG32+AJ32+AM32+AP32 -> 19950
A33: 21 | B33: ПандаЭкспо | E33: =25 -> 25 | F33: 3990 | O33: =E33*F33 -> 99750 | S33: =F33*G33 -> 0 | T33: =G33*H33 -> 0 | V33: =I33*J33 -> 0 | AS33: =I33+L33+O33+R33+U33+X33+AA33+AD33+AG33+AJ33+AM33+AP33 -> 99750
A34: 22 | B34: ООО "АДЕН МЕТАЛ"» | E34: 30 | F34: 3800 | O34: =E34*F34 -> 114000 | R34: =E34*F34 -> 114000 | U34: 76000 | X34: 76000 | AA34: 76000 | AD34: 76000 | AG34: 76000 | AJ34: 76000 | AM34: 76000 | AP34: 76000 | AS34: =I34+L34+O34+R34+U34+X34+AA34+AD34+AG34+AJ34+AM34+AP34 -> 836000
A35: 23 | B35: АО КМПО "КАЗАНСКОЕ МОТОРОСТРОИТЕЛЬНОЕ ПРОИЗВОДСТВЕННОЕ ОБЪЕДИНЕНИЕ | E35: 30 | F35: 3800 | O35: =E35*F35 -> 114000 | R35: =E35*F35 -> 114000 | U35: =3800*20 -> 76000 | X35: =3800*30 -> 114000 | AA35: 76000 | AD35: 76000 | AG35: 76000 | AJ35: 76000 | AM35: 76000 | AP35: 76000 | AS35: =I35+L35+O35+R35+U35+X35+AA35+AD35+AG35+AJ35+AM35+AP35 -> 874000
A36: 24 | B36: Фортекс | E36: 100 | F36: 3800 | H36: 0 | L36: 19950 | O36: =E36*F36 -> 380000 | R36: =F35*E36 -> 380000 | U36: =3800*50 -> 190000 | X36: =3800*60 -> 228000 | AA36: =3800*80 -> 304000 | AD36: =3800*100 -> 380000 | AG36: =3800*120 -> 456000 | AJ36: =3800*150 -> 570000 | AM36: =3800*159 -> 604200 | AP36: =3800*170 -> 646000 | AS36: =I36+L36+O36+R36+U36+X36+AA36+AD36+AG36+AJ36+AM36+AP36 -> 4158150
B37: ИТОГО Новая разработка | H37: =H30+H32+H33+H34+H35+H36 -> 0 | I37: 0 | J37: 0 | K37: 0 | L37: =SUM(L30:L36) -> 182820 | M37: =SUM(M30:M36) -> 0 | N37: =SUM(N30:N36) -> 0 | O37: =SUM(O30:O36) -> 707750 | P37: =SUM(P30:P36) -> 0 | Q37: =SUM(Q30:Q36) -> 0 | R37: =SUM(R30:R36) -> 608000 | S37: =SUM(S30:S36) -> 0 | ... AS37: =SUM(AS30:AS36) -> 6130770
H38: 46048 | L38: фев.26 | O38: 46107 | R38: 46138 | U38: май.26 | X38: 46199 | AA38: 46229 | AD38: 46260 | AG38: сен.26 | AJ38: 46321 | AM38: ноя.26 | AP38: 46382 | AT38: бюджет 2026
B39: Выручка сервера | H39: =H40+H41+H42 -> 20000 | I39: =I40+I41+I42 -> 0 | J39: =J40+J41+J42 -> 0 | K39: =K40+K41+K42 -> 0 | L39: =L40+L41+L42 -> 25600 | M39: =M40+M41+M42 -> 0 | N39: =N40+N41+N42 -> 0 | O39: =O40+O41+O42 -> 32000 | ... AS39: =AS40+AS41+AS42 -> 397600 | AT39: ='Бюджет 2026'!S7 -> 400000
B40: ООО "ЗЕЛПАК" | H40: =5000*3 -> 15000 | L40: =6400*3 -> 19200 | O40: =6400*3 -> 19200 | R40: =6400*3 -> 19200 | U40: =6400*3 -> 19200 | X40: =6400*3 -> 19200 | AA40: =6400*3 -> 19200 | AD40: =6400*3 -> 19200 | AG40: =6400*3 -> 19200 | AJ40: =6400*3 -> 19200 | AM40: =6400*3 -> 19200 | AP40: =6400*3 -> 19200 | AS40: =SUM(H40:AR40) -> 226200
B41: ИП Абрамова Дарья Валерьевна | H41: =5000 -> 5000 | L41: =6400 -> 6400 | O41: =6400 -> 6400 | R41: =6400 -> 6400 | U41: =6400 -> 6400 | X41: =6400 -> 6400 | AA41: =6400 -> 6400 | AD41: =6400 -> 6400 | AG41: =6400 -> 6400 | AJ41: =6400 -> 6400 | AM41: =6400 -> 6400 | AP41: =6400 -> 6400 | AS41: =SUM(H41:AR41) -> 75400
B42: новая продажа | O42: 6400 | R42: 6400 | U42: 6400 | X42: 6400 | AA42: 6400 | AD42: 12800 | AG42: 12800 | AJ42: 12800 | AM42: =6400*2 -> 12800 | AP42: =6400*2 -> 12800 | AS42: =SUM(H42:AR42) -> 96000
B43: Выручка коробки | H43: =H44+H45+H46+H47+H48+H49+H50+H54+H55+H56 -> 71800 | I43: =I44+I45+I46+I47+I48+I49+I50+I54+I55+I56 -> 0 | J43: =J44+J45+J46+J47+J48+J49+J50+J54+J55+J56 -> 0 | K43: =K44+K45+K46+K47+K48+K49+K50+K54+K55+K56 -> 0 | L43: =L44+L45+L46+L47+L48+L49+L50+L54+L55+L56 -> 221400 | M43: =M44+M45+M46+M47+M48+M49+M50+M54+M55+M56 -> 0 | N43: =N44+N45+N46+N47+N48+N49+N50+N54+N55+N56 -> 0 | O43: =O44+O45+O46+O47+O48+O49+O50+O54+O55+O56 -> 164000 | ... Z43: =Z44+Z45+Z46+Z47+Z48+Z49+Z50+Z54+Z55+Z56 -> 0 | AA43: =AA44+AA45+AA46+AA47+AA48+AA49+AA50+AA54+AA55+AA56+AA51+AA52+AA53 -> 215000 | AB43: =AB44+AB45+AB46+AB47+AB48+AB49+AB50+AB54+AB55+AB56 -> 0 | AC43: =AC44+AC45+AC46+AC47+AC48+AC49+AC50+AC54+AC55+AC56 -> 0 | AD43: =AD44+AD45+AD46+AD47+AD48+AD49+AD50+AD54+AD55+AD56 -> 160000 | AE43: =AE44+AE45+AE46+AE47+AE48+AE49+AE50+AE54+AE55+AE56 -> 0 | AF43: =AF44+AF45+AF46+AF47+AF48+AF49+AF50+AF54+AF55+AF56 -> 0 | AG43: =AG44+AG45+AG46+AG47+AG48+AG49+AG50+AG54+AG55+AG56 -> 100000 | AH43: =AH44+AH45+AH46+AH47+AH48+AH49+AH50+AH54+AH55+AH56 -> 0 | AI43: =AI44+AI45+AI46+AI47+AI48+AI49+AI50+AI54+AI55+AI56 -> 0 | ... AQ43: =AQ44+AQ45+AQ46+AQ47+AQ48+AQ49+AQ50+AQ54+AQ55+AQ56 -> 0 | AS43: =SUM(H43:AR43) -> 1597200
B44: ИП Саипов Арсен Салмурзаевич | AM44: 55000 | AS44: =SUM(H44:AR44) -> 55000
B45: ИП Абрамова Дарья Валерьевна | X45: 50000 | AS45: =SUM(H45:AR45) -> 50000
B46: Мангала | O46: 57000 | AS46: =SUM(H46:AR46) -> 57000
B47: рэк 2 | AP47: 55000 | AS47: =SUM(H47:AR47) -> 55000
B48: Симон Электрик | O48: 57000 | AS48: =SUM(H48:AR48) -> 57000
B49: технокомп | C49: ДОГОВОР № 09/09/2025 на Интеграцию 1C по API с B2B | AD49: 55000 | AS49: =SUM(H49:AR49) -> 55000
B50: пакмен 2 | AD50: 55000 | AS50: =SUM(H50:AR50) -> 55000
B51: Жилстрой | AA51: 55000
B52: Вилар | AA52: 55000
B53: Виста групп | AA53: 55000
B54: Инфинити | L54: 55000 | AS54: =SUM(H54:AR54) -> 55000
B55: Кертинг | H55: =51700+20100 -> 71800 | L55: 150000 | AP55: 55000 | AS55: =SUM(H55:AR55) -> 276800
B56: прочие | L56: 16400 | O56: 50000 | R56: 100000 | U56: 50000 | X56: 50000 | AA56: 50000 | AD56: 50000 | AG56: 100000 | AJ56: 100000 | AM56: 100000 | AP56: 50000 | AS56: =SUM(H56:AR56) -> 716400
B57: Выручка поддержка | H57: 83400 | L57: =3800*10 -> 38000 | O57: =3800*10 -> 38000 | R57: =3800*10 -> 38000 | U57: =3800*15 -> 57000 | X57: =3800*15 -> 57000 | AA57: =3800*15 -> 57000 | AD57: =3800*15 -> 57000 | AG57: =3800*10 -> 38000 | AJ57: =3800*10 -> 38000 | AM57: =3800*10 -> 38000 | AP57: =3800*15 -> 57000 | AS57: =SUM(B57:AR57) -> 596400
B58: прочие | F58: 3570 | H58: 35700 | AB58: 0 | AS58: =SUM(H58:AR58) -> 35700
H59: январь | L59: февраль | O59: март | R59: апрель | U59: май | X59: июнь | AA59: июль | AD59: август | AG59: сентябрь | AJ59: октябрь | AM59: ноябрь | AS59: =SUM(H59:AR59) -> 0
B60: Выручка продукты | M60: 0 | N60: 0 | P60: 0 | Q60: 0 | R60: 0 | S60: 0 | T60: 0 | V60: 0 | W60: 0 | X60: 0 | Y60: 0 | Z60: 0 | AA60: 0 | AB60: 0 | AC60: 0 | AE60: 0 | AF60: 0 | AG60: 0 | AH60: 0 | AI60: 0 | AK60: 0 | AL60: 0 | AM60: 0 | AN60: 0 | AO60: 0 | AQ60: 0 | AR60: 0
B61: СТГ ГВАРД | D61: ООО "СТГ ГВАРД" | E61: 45775 | F61: 46140 | G61: 30 000,00 р | R61: =34000*1.05 -> 35700 | AS61: =SUM(H61:AR61) -> 35700
B62: РЭК | C62: 45880 | D62: ДИС-3 | E62: 45824 | F62: 46189 | G62: 30 000,00 р | X62: =34000*1.05 -> 35700 | AS62: =SUM(H62:AR62) -> 35700
B63: ИП Александров Юрий Александрович | C63: 45957 | D63: НПП СПЕКТР | E63: 45846 | F63: 46211 | G63: 30 000,00 р | AA63: =34000*1.05 -> 35700 | AS63: =SUM(H63:AR63) -> 35700
B64: ИП Дрынова Наталья Валерьевна | C64: 30.06.2025, год бесплатно | D64: ИП Дрынова Наталья Валерьевна | E64: 46006 | F64: 46371 | G64: 49 000,00 р | AP64: =59000*1.05 -> 61950 | AS64: =SUM(H64:AR64) -> 61950
B65: ИП Семашкина Анна Александровна | C65: возврат | D65: ООО "Примум Мебель" | E65: 46021 | F65: 46386 | G65: 53 100,00 р | AP65: =59000*1.05 -> 61950 | AS65: =SUM(H65:AR65) -> 61950
B66: ДИС-3 | C66: 45720 | D66: ООО "ИНАРИ ГРУПП" | E66: 29 авугста 2025 | F66: 29 авугста 2026 | G66: 29 000,00 р | AD66: =34000*1.05 -> 35700 | AS66: =SUM(H66:AR66) -> 35700
B67: СПЕКТР | C67: 45715 | D67: ИП Семашкина Анна Александровна (ООО "Правда") | E67: 46000 | F67: 46365 | G67: 49 000,00 р | AP67: 61950 | AS67: =SUM(H67:AR67) -> 61950
B68: Соглашение | C68: 45807 | D68: ООО "РЭК" | E68: 45922 | F68: 46287 | G68: 29 000,00 р | AG68: =34000*1.05 -> 35700 | AS68: =SUM(H68:AR68) -> 35700
B69: Примум мебель | C69: 46017 | D69: ООО "ЦТС" | E69: 45925 | F69: 46290 | G69: 49 000,00 р | AG69: =59000*1.05 -> 61950 | AS69: =SUM(H69:AR69) -> 61950
B70: Инари групп | C70: 45877 | D70: ИП Александров Юрий Александрович | E70: 46000 | F70: 46365 | G70: 49 000,00 р | AP70: 61950 | AS70: =SUM(H70:AR70) -> 61950
B71: ЦТС | C71: 46259 | D71: ИП Хабаров Александр Юрьевич | E71: 45986 | F71: 46351 | G71: 59 000,00 р | AM71: 61950 | AS71: =SUM(H71:AR71) -> 61950
B72: Петренко максим викторович | C72: 45896 | D72: ООО "ХИТСАД" | E72: 45987 | F72: 45987 | G72: 59 000,00 р | AM72: 61950 | AS72: =SUM(H72:AR72) -> 61950
B73: Технокомп | C73: ДОГОВОР № 09/09/2025 | D73: ИП Колосов Александр Васильевич | E73: 46045 | F73: 46045 | G73: 61 950,00 р | AS73: =SUM(H73:AR73) -> 0
B74: ИП Колосов | C74: на Интеграцию 1C по API с B2B | H74: 53100 | AS74: =SUM(H74:AR74) -> 53100
B75: Алимп | C75: 46050 | I75: 61950 | L75: 61950 | O75: 61950 | R75: 61950 | U75: 61950 | X75: 61950 | AA75: 61950 | AD75: 61950 | AG75: 61950 | AJ75: 61950 | AM75: 61950 | AP75: 61950 | AS75: =SUM(H75:AR75) -> 743400
B76: Детали Опт | I76: 61950 | L76: 61950 | O76: 61950 | X76: 61950 | AA76: 61950 | AD76: 61950 | AG76: 61950 | AJ76: 61950 | AS76: =SUM(H76:AR76) -> 495600
B77: ПандаЭкспо | O77: 100000 | X77: 100000 | AM77: 100000 | AS77: =SUM(H77:AR77) -> 300000
B78: Прочие | AS78: =SUM(H78:AR78) -> 0
B79: Итого выручка: | H79: =SUM(H60:H78) -> 53100 | I79: =SUM(I60:I78) -> 123900 | J79: =SUM(J60:J78) -> 0 | K79: =SUM(K60:K78) -> 0 | L79: =SUM(L60:L78) -> 123900 | M79: =SUM(M60:M78) -> 0 | N79: =SUM(N60:N78) -> 0 | O79: =SUM(O60:O78) -> 223900 | ... AR79: =SUM(AR60:AR78) -> 0 | AS79: =SUM(AS61:AS78) -> 2204250
B81: Себестоимость
H83: Январь 2024 | L83: Февраль 2024 | O83: Март 2024 | R83: Апрель 2024 | U83: Май 2024 | X83: Июнь 2024 | AA83: Июль 2024 | AD83: Август 2024 | AG83: Сентябрь 2024 | AJ83: Октябрь 2024 | AM83: Ноябрь 2024 | AP83: Декабрь 2024 | AT83: бюджет 2026
B84: Себестоимость от продаж
B85: Себестоимость коробки | H85: =H43*0.5*(-1) -> -35900 | I85: =I43*0.5*(-1) -> 0 | J85: =J43*0.5*(-1) -> 0 | K85: =K43*0.5*(-1) -> 0 | L85: =L43*0.5*(-1) -> -110700 | M85: =M43*0.5*(-1) -> 0 | N85: =N43*0.5*(-1) -> 0 | O85: =O43*0.5*(-1) -> -82000 | ... AT85: =AT43*0.5*(-1) -> 0 | AU85: Сысоев В.С.
B86: Итого себестоимость: | AU86: Сысоев В.С.
B87: Итого прибыль: | AU87: Сысоев В.С.
B88: Рентабельность: | AU88: Сысоев В.С.
AU89: Павлова Д.И.
B90: Себестоимость прочая | AU90: Макшанова Л.М.
B93: Простой
B94: Оплата попадосов
B95: Выплата заработной платы разработка
B96: Оплата аналитики | H96: Январь 2024 | L96: Февраль 2024 | O96: Март 2024 | R96: Апрель 2024 | U96: Май 2024 | X96: Июнь 2024 | AA96: Июль 2024 | AD96: Август 2024 | AG96: Сентябрь 2024 | AJ96: Октябрь 2024 | AM96: Ноябрь 2024 | AP96: Декабрь 2024 | AT96: бюджет 2026
B97: Откат ментам
B98: Бонус отдела продаж | AU98: Львов С.А.
B99: Итого Себестоимость прочая:
B100: Итого прибыль:
B101: Рентабельность:
B103: Операционные расходы
H104: Январь 2024 | L104: Февраль 2024 | O104: Март 2024 | R104: Апрель 2024 | U104: Май 2024 | X104: Июнь 2024 | AA104: Июль 2024 | AD104: Август 2024 | AG104: Сентябрь 2024 | AJ104: Октябрь 2024 | AM104: Ноябрь 2024 | AP104: Декабрь 2024 | AT104: бюджет 2026
B106: Выплата заработной платы(Операционные) | AT106: 3 840 000,00 | AU106: Макшанова Л.М.
...

Sheet Сысоев
H3: Икс ком | I3: Артис | J3: Симон | K3: Ууаз | L3: Газпром | M3: Прочее | N3: Средняя ставка | O3: Сезонность (справочно) | P3: План | Q3: аналитика Федоров
G4: Часы (предел) | H4: 450 | I4: 150 | J4: 40 | K4: 200 | L4: 77 | M4: 150 | Q4: =I4*150 -> 22500
C5: Я | D5: 1248000 | H5: 150 | I5: 100 | J5: 40 | K5: 0 | L5: 0 | M5: 100 | N5: 3200 | O5: 0.3 | P5: =(H5+I5+J5+K5+L5+M5)*N5 -> 1248000 | Q5: =I5*150 -> 15000
C6: Ф | D6: 2508000 | H6: 400 | I6: 100 | J6: 40 | K6: 50 | L6: 20 | M6: 150 | N6: 3300 | O6: 0.7 | P6: =(H6+I6+J6+K6+L6+M6)*N6 -> 2508000 | Q6: =I6*150 -> 15000
C7: М | D7: 3104000 | H7: 450 | I7: 150 | J7: 40 | K7: 100 | L7: 30 | M7: 200 | N7: 3200 | O7: 0.8 | P7: =(H7+I7+J7+K7+L7+M7)*N7 -> 3104000 | Q7: =I7*150 -> 22500
C8: А | D8: 3135000 | H8: 450 | I8: 130 | J8: 40 | K8: 100 | L8: 30 | M8: 200 | N8: 3300 | O8: 0.85 | P8: =(H8+I8+J8+K8+L8+M8)*N8 -> 3135000 | Q8: =I8*150 -> 19500
C9: М | D9: 2310000 | H9: 300 | I9: 100 | J9: 40 | K9: 100 | L9: 60 | M9: 100 | N9: 3300 | O9: 0.65 | P9: =(H9+I9+J9+K9+L9+M9)*N9 -> 2310000 | Q9: =I9*150 -> 15000
C10: И | D10: 3185000 | H10: 400 | I10: 120 | J10: 40 | K10: 150 | L10: 50 | M10: 150 | N10: 3500 | O10: 0.75 | P10: =(H10+I10+J10+K10+L10+M10)*N10 -> 3185000 | Q10: =I10*150 -> 18000
C11: И | D11: 3276000 | H11: 400 | I11: 120 | J11: 40 | K11: 150 | L11: 0 | M11: 150 | N11: 3600 | O11: 0.75 | P11: =(H11+I11+J11+K11+L11+M11)*N11 -> 3096000 | Q11: =I11*150 -> 18000
C12: А | D12: 3420000 | H12: 400 | I12: 100 | J12: 40 | K12: 150 | L12: 0 | M12: 200 | N12: 3600 | O12: 0.8 | P12: =(H12+I12+J12+K12+L12+M12)*N12 -> 3204000 | Q12: =I12*150 -> 15000
C13: С | D13: 4014500 | H13: 450 | I13: 100 | J13: 40 | K13: 200 | L13: 0 | M13: 230 | N13: 3700 | O13: 0.85 | P13: =(H13+I13+J13+K13+L13+M13)*N13 -> 3774000 | Q13: =I13*150 -> 15000
C14: О | D14: 4273500 | H14: 450 | I14: 150 | J14: 40 | K14: 200 | L14: 0 | M14: 250 | N14: 3700 | O14: 0.95 | P14: =(H14+I14+J14+K14+L14+M14)*N14 -> 4033000 | Q14: =I14*150 -> 22500
C15: Н | D15: 4712000 | H15: 480 | I15: 150 | J15: 40 | K15: 200 | L15: 0 | M15: 300 | N15: 3800 | O15: 0.95 | P15: =(H15+I15+J15+K15+L15+M15)*N15 -> 4446000 | Q15: =I15*150 -> 22500
C16: Д | D16: 5187000 | H16: 500 | I16: 150 | J16: 40 | K16: 250 | L16: 0 | M16: 350 | N16: 3800 | O16: 1.2 | P16: =(H16+I16+J16+K16+L16+M16)*N16 -> 4902000 | Q16: =I16*150 -> 22500
P17: =SUM(P5:P16) -> 38945000

Sheet копия заполнить отв. Макшанова
A1: 0 | B1: Ответственный | C1: Месяц | D1: Квартал | E1: План | F1: Факт | G1: Комментарий
A2: 01.1.Выручка от продаж разработки | B2: Макшанова Л.М. | C2: 01.Январь | D2: 1 | E2: ='Макшанова'!H37 -> 0
A3: 02.1.Выручка сервера | B3: Макшанова Л.М. | C3: 01.Январь | D3: 1 | E3: =5000*4 -> 20000
A4: 03.1.Выручка коробки | B4: Макшанова Л.М. | C4: 01.Январь | D4: 1 | E4: ='Бюджет 2026'!S8/12 -> 208333.33
A5: 04.1.Выручка поддержка | B5: Макшанова Л.М. | C5: 01.Январь | D5: 1 | E5: ='Бюджет 2026'!S9/12 -> 291666.67
A6: 05.1.Выручка продукты | B6: Макшанова Л.М. | C6: 01.Январь | D6: 1 | E6: =59000*2 -> 118000
A7: 06.Себестоимость от продаж | B7: Сысоев В.С. | C7: 01.Январь | D7: 1 | E7: =J7*0.35*(-1) -> -212800 | J7: =E2+E29 -> 608000
A8: 07.Себестоимость коробки | B8: Макшанова Л.М. | C8: 01.Январь | D8: 1 | E8: =E4/0.5*(-1) -> -416666.67
A9: 13.Бонус отдела продаж | B9: Макшанова Л.М. | C9: 01.Январь | D9: 1 | E9: -20000
A10: 15.Выплата заработной платы(Развитие) | B10: Макшанова Л.М. | C10: 01.Январь | D10: 1 | E10: -320000
A11: 01.1.Выручка от продаж разработки | B11: Макшанова Л.М. | C11: 02.Февраль | D11: 1 | E11: ='Макшанова'!L37 -> 182820
A12: 02.1.Выручка сервера | B12: Макшанова Л.М. | C12: 02.Февраль | D12: 1 | E12: 30500
A13: 03.1.Выручка коробки | B13: Макшанова Л.М. | C13: 02.Февраль | D13: 1 | E13: ='Бюджет 2026'!S8/12 -> 208333.33
A14: 04.1.Выручка поддержка | B14: Макшанова Л.М. | C14: 02.Февраль | D14: 1 | E14: ='Бюджет 2026'!S9/12 -> 291666.67
A15: 05.1.Выручка продукты | B15: Макшанова Л.М. | C15: 02.Февраль | D15: 1 | E15: =59000*3 -> 177000
A16: 06.Себестоимость от продаж | B16: Сысоев В.С. | C16: 02.Февраль | D16: 1 | E16: =J16*0.35*(-1) -> -183687 | J16: =E11+E38 -> 524820
A17: 07.Себестоимость коробки | B17: Макшанова Л.М. | C17: 02.Февраль | D17: 1 | E17: =E13*0.5*(-1) -> -104166.67
A18: 13.Бонус отдела продаж | B18: Макшанова Л.М. | C18: 02.Февраль | D18: 1 | E18: -33333.333
A19: 15.Выплата заработной платы(Развитие) | B19: Макшанова Л.М. | C19: 02.Февраль | D19: 1 | E19: -320000
A20: 01.1.Выручка от продаж разработки | B20: Макшанова Л.М. | C20: 03.Март | D20: 1 | E20: ='Макшанова'!O37 -> 707750
A21: 02.1.Выручка сервера | B21: Макшанова Л.М. | C21: 03.Март | D21: 1 | E21: =30500+6100 -> 36600
A22: 03.1.Выручка коробки | B22: Макшанова Л.М. | C22: 03.Март | D22: 1 | E22: ='Бюджет 2026'!S8/12 -> 208333.33
A23: 04.1.Выручка поддержка | B23: Макшанова Л.М. | C23: 03.Март | D23: 1 | E23: =E5 -> 291666.67
A24: 05.1.Выручка продукты | B24: Макшанова Л.М. | C24: 03.Март | D24: 1 | E24: ='Бюджет 2026'!S10/12 -> 250000
A25: 06.Себестоимость от продаж | B25: Сысоев В.С. | C25: 03.Март | D25: 1 | E25: =J25*0.35*(-1) -> -394012.5 | J25: =E20+E47 -> 1125750
A26: 07.Себестоимость коробки | B26: Макшанова Л.М. | C26: 03.Март | D26: 1 | E26: =E22*0.5*(-1) -> -104166.67
A27: 13.Бонус отдела продаж | B27: Макшанова Л.М. | C27: 03.Март | D27: 1 | E27: -33333.333
A28: 15.Выплата заработной платы(Развитие) | B28: Макшанова Л.М. | C28: 03.Март | D28: 1 | E28: -320000
A29: 01.1.Выручка от продаж разработки | B29: Макшанова Л.М. | C29: 04.Апрель | D29: 2 | E29: ='Макшанова'!R37 -> 608000
A30: 02.1.Выручка сервера | B30: Макшанова Л.М. | C30: 04.Апрель | D30: 2 | E30: =30500+6100 -> 36600
A31: 03.1.Выручка коробки | B31: Макшанова Л.М. | C31: 04.Апрель | D31: 2 | E31: ='Бюджет 2026'!S8/12 -> 208333.33
A32: 04.1.Выручка поддержка | B32: Макшанова Л.М. | C32: 04.Апрель | D32: 2 | E32: ='Бюджет 2026'!S9/12 -> 291666.67
A33: 05.1.Выручка продукты | B33: Макшанова Л.М. | C33: 04.Апрель | D33: 2 | E33: ='Бюджет 2026'!S10/12 -> 250000
A34: 06.Себестоимость от продаж | B34: Сысоев В.С. | C34: 04.Апрель | D34: 2 | E34: =J34*0.35*(-1) -> -359100 | J34: =E29+E56 -> 1026000
A35: 07.Себестоимость коробки | B35: Макшанова Л.М. | C35: 04.Апрель | D35: 2 | E35: =E13*0.5*(-1) -> -104166.67
A36: 13.Бонус отдела продаж | B36: Макшанова Л.М. | C36: 04.Апрель | D36: 2 | E36: -33333.333
A37: 15.Выплата заработной платы(Развитие) | B37: Макшанова Л.М. | C37: 04.Апрель | D37: 2 | E37: -320000
A38: 01.1.Выручка от продаж разработки | B38: Макшанова Л.М. | C38: 05.Май | D38: 2 | E38: ='Макшанова'!U37 -> 342000
A39: 02.1.Выручка сервера | B39: Макшанова Л.М. | C39: 05.Май | D39: 2 | E39: 36600
A40: 03.1.Выручка коробки | B40: Макшанова Л.М. | C40: 05.Май | D40: 2 | E40: ='Бюджет 2026'!S8/12 -> 208333.33
A41: 04.1.Выручка поддержка | B41: Макшанова Л.М. | C41: 05.Май | D41: 2 | E41: ='Бюджет 2026'!S9/12 -> 291666.67
A42: 05.1.Выручка продукты | B42: Макшанова Л.М. | C42: 05.Май | D42: 2 | E42: =#REF!/12 -> #REF!
A43: 06.Себестоимость от продаж | B43: Сысоев В.С. | C43: 05.Май | D43: 2 | E43: =J43*0.35*(-1) -> -305900 | J43: =E38+E65 -> 874000
A44: 07.Себестоимость коробки | B44: Макшанова Л.М. | C44: 05.Май | D44: 2 | E44: =E40*0.5*(-1) -> -104166.67
A45: 13.Бонус отдела продаж | B45: Макшанова Л.М. | C45: 05.Май | D45: 2 | E45: -33333.333
A46: 15.Выплата заработной платы(Развитие) | B46: Макшанова Л.М. | C46: 05.Май | D46: 2 | E46: -320000
A47: 01.1.Выручка от продаж разработки | B47: Макшанова Л.М. | C47: 06.Июнь | D47: 2 | E47: ='Макшанова'!X37 -> 418000
A48: 02.1.Выручка сервера | B48: Макшанова Л.М. | C48: 06.Июнь | D48: 2 | E48: ='Бюджет 2026'!S7/12 -> 33333.333
A49: 03.1.Выручка коробки | B49: Макшанова Л.М. | C49: 06.Июнь | D49: 2 | E49: 208333.33
A50: 04.1.Выручка поддержка | B50: Макшанова Л.М. | C50: 06.Июнь | D50: 2 | E50: ='Бюджет 2026'!S9/12 -> 291666.67
A51: 05.1.Выручка продукты | B51: Макшанова Л.М. | C51: 06.Июнь | D51: 2 | E51: =E23 -> 291666.67
A52: 06.Себестоимость от продаж | B52: Сысоев В.С. | C52: 06.Июнь | D52: 2 | E52: =J52*0.35*(-1) -> -359100 | J52: =E47+E74 -> 1026000
A53: 07.Себестоимость коробки | B53: Макшанова Л.М. | C53: 06.Июнь | D53: 2 | E53: =E49*0.5*(-1) -> -104166.67
A54: 13.Бонус отдела продаж | B54: Макшанова Л.М. | C54: 06.Июнь | D54: 2 | E54: -33333.333
A55: 15.Выплата заработной платы(Развитие) | B55: Макшанова Л.М. | C55: 06.Июнь | D55: 2 | E55: -320000
A56: 01.1.Выручка от продаж разработки | B56: Макшанова Л.М. | C56: 07.Июль | D56: 3 | E56: ='Макшанова'!X37 -> 418000
A57: 02.1.Выручка сервера | B57: Макшанова Л.М. | C57: 07.Июль | D57: 3 | E57: =36600+3500 -> 40100
A58: 03.1.Выручка коробки | B58: Макшанова Л.М. | C58: 07.Июль | D58: 3 | E58: ='Бюджет 2026'!S8/12 -> 208333.33
A59: 04.1.Выручка поддержка | B59: Макшанова Л.М. | C59: 07.Июль | D59: 3 | E59: 291666.67
A60: 05.1.Выручка продукты | B60: Макшанова Л.М. | C60: 07.Июль | D60: 3 | E60: 250000
A61: 06.Себестоимость от продаж | B61: Сысоев В.С. | C61: 07.Июль | D61: 3 | E61: =J61*0.35*(-1) -> -399000 | J61: =E56+E83 -> 1140000
A62: 07.Себестоимость коробки | B62: Макшанова Л.М. | C62: 07.Июль | D62: 3 | E62: =E58*0.5*(-1) -> -104166.67
A63: 13.Бонус отдела продаж | B63: Макшанова Л.М. | C63: 07.Июль | D63: 3 | E63: -33333.333
A64: 15.Выплата заработной платы(Развитие) | B64: Макшанова Л.М. | C64: 07.Июль | D64: 3 | E64: -320000
A65: 01.1.Выручка от продаж разработки | B65: Макшанова Л.М. | C65: 08.Август | D65: 3 | E65: ='Макшанова'!AD37 -> 532000
A66: 02.1.Выручка сервера | B66: Макшанова Л.М. | C66: 08.Август | D66: 3 | E66: 36600
A67: 03.1.Выручка коробки | B67: Макшанова Л.М. | C67: 08.Август | D67: 3 | E67: 208333.33
A68: 04.1.Выручка поддержка | B68: Макшанова Л.М. | C68: 08.Август | D68: 3 | E68: 291666.67
A69: 05.1.Выручка продукты | B69: Макшанова Л.М. | C69: 08.Август | D69: 3 | E69: 250000
A70: 06.Себестоимость от продаж | B70: Сысоев В.С. | C70: 08.Август | D70: 3 | E70: =J70*0.35*(-1) -> -450870 | J70: =E65+E92 -> 1288200
A71: 07.Себестоимость коробки | B71: Макшанова Л.М. | C71: 08.Август | D71: 3 | E71: ='Бюджет 2026'!S8/12*0.5*(-1) -> -104166.67
A72: 13.Бонус отдела продаж | B72: Макшанова Л.М. | C72: 08.Август | D72: 3 | E72: -33333.333
A73: 15.Выплата заработной платы(Развитие) | B73: Макшанова Л.М. | C73: 08.Август | D73: 3 | E73: -320000
A74: 01.1.Выручка от продаж разработки | B74: Макшанова Л.М. | C74: 09.Сентябрь | D74: 3 | E74: ='Макшанова'!AG37 -> 608000
A75: 02.1.Выручка сервера | B75: Макшанова Л.М. | C75: 09.Сентябрь | D75: 3 | E75: 36600
A76: 03.1.Выручка коробки | B76: Макшанова Л.М. | C76: 09.Сентябрь | D76: 3 | E76: 208333.33
A77: 04.1.Выручка поддержка | B77: Макшанова Л.М. | C77: 09.Сентябрь | D77: 3 | E77: 291666.67
A78: 05.1.Выручка продукты | B78: Макшанова Л.М. | C78: 09.Сентябрь | D78: 3 | E78: 250000
A79: 06.Себестоимость от продаж | B79: Сысоев В.С. | C79: 09.Сентябрь | D79: 3 | E79: =J79*0.35*(-1) -> -492100 | J79: =E74+E101 -> 1406000
A80: 07.Себестоимость коробки | B80: Макшанова Л.М. | C80: 09.Сентябрь | D80: 3 | E80: =E76*0.5*(-1) -> -104166.67
A81: 13.Бонус отдела продаж | B81: Макшанова Л.М. | C81: 09.Сентябрь | D81: 3 | E81: -33333.333
A82: 15.Выплата заработной платы(Развитие) | B82: Макшанова Л.М. | C82: 09.Сентябрь | D82: 3 | E82: -320000
A83: 01.1.Выручка от продаж разработки | B83: Макшанова Л.М. | C83: 10.Октябрь | D83: 4 | E83: ='Макшанова'!AJ37 -> 722000
A84: 02.1.Выручка сервера | B84: Макшанова Л.М. | C84: 10.Октябрь | D84: 4 | E84: 36600
A85: 03.1.Выручка коробки | B85: Макшанова Л.М. | C85: 10.Октябрь | D85: 4 | E85: 208333.33
A86: 04.1.Выручка поддержка | B86: Макшанова Л.М. | C86: 10.Октябрь | D86: 4 | E86: ='Бюджет 2026'!S9/12 -> 291666.67
A87: 05.1.Выручка продукты | B87: Макшанова Л.М. | C87: 10.Октябрь | D87: 4 | E87: ='Бюджет 2026'!S10/12 -> 250000
A88: 06.Себестоимость от продаж | B88: Сысоев В.С. | C88: 10.Октябрь | D88: 4 | E88: =J88*0.35*(-1) -> #VALUE! | J88: =E83+E110 -> #VALUE!
A89: 07.Себестоимость коробки | B89: Макшанова Л.М. | C89: 10.Октябрь | D89: 4 | E89: =E85*0.5*(-1) -> -104166.67
A90: 13.Бонус отдела продаж | B90: Макшанова Л.М. | C90: 10.Октябрь | D90: 4 | E90: -33333.333
A91: 15.Выплата заработной платы(Развитие) | B91: Макшанова Л.М. | C91: 10.Октябрь | D91: 4 | E91: -320000
A92: 01.1.Выручка от продаж разработки | B92: Макшанова Л.М. | C92: 11.Ноябрь | D92: 4 | E92: ='Макшанова'!AM37 -> 756200
A93: 02.1.Выручка сервера | B93: Макшанова Л.М. | C93: 11.Ноябрь | D93: 4 | E93: =36600+6100 -> 42700
A94: 03.1.Выручка коробки | B94: Макшанова Л.М. | C94: 11.Ноябрь | D94: 4 | E94: ='Бюджет 2026'!S8/12 -> 208333.33
A95: 04.1.Выручка поддержка | B95: Макшанова Л.М. | C95: 11.Ноябрь | D95: 4 | E95: ='Бюджет 2026'!S9/12 -> 291666.67
A96: 05.1.Выручка продукты | B96: Макшанова Л.М. | C96: 11.Ноябрь | D96: 4 | E96: 250000
A97: 06.Себестоимость от продаж | B97: Сысоев В.С. | C97: 11.Ноябрь | D97: 4 | E97: =J97*0.35*(-1) -> -152670 | J97: =E92+E119 -> 436200
A98: 07.Себестоимость коробки | B98: Макшанова Л.М. | C98: 11.Ноябрь | D98: 4 | E98: =E94*0.5*(-1) -> -104166.67
A99: 13.Бонус отдела продаж | B99: Макшанова Л.М. | C99: 11.Ноябрь | D99: 4 | E99: -33333.333
A100: 15.Выплата заработной платы(Развитие) | B100: Макшанова Л.М. | C100: 11.Ноябрь | D100: 4 | E100: -320000
...

Sheet Отклонение от  плана ЛСА
B1: Отклонение плана рук от плана ЛСА
C3: План ЛСА | D3: Отклонение
C4: 12000000 | D4: =B4-C4 -> -5869230
C5: 35186000 | D5: =B5-C5 -> 901665
C6: 400000 | D6: =B6-C6 -> -2400
C7: 2500000 | D7: =B7-C7 -> -902800
C8: 3500000 | D8: =B8-C8 -> -2903600
C9: 3000000 | D9: =B9-C9 -> -981600
C10: 16739095 | D10: =B10+C10 -> 1157643
C11: 1250000 | D11: =B11+C11 -> 321800
C12: 1000000 | D12: =B12+C12 -> 226400
C13: 500000 | D13: =B13+C13 -> 475000
C14: 3000000 | D14: =B14+C14 -> 1920000
C15: 3000000 | D15: =B15+C15 -> 2350000
C16: 4000000 | D16: =B16+C16 -> 2277340
C17: 400000 | D17: =B17+C17 -> -1883311.1
C18: 1872000 | D18: =B18+C18 -> -2128000
C19: 3840000 | D19: =B19+C19 -> 3453333.3
C20: 1000000 | D20: =B20+C20 -> -560000
C21: 1000000 | D21: =B21+C21 -> -2840000
... C31: 3970100.5 | D31: =B31+C31 -> 3700000.5
C32: =SUM(C4:C31) -> 1.090973e+08 | D32: =SUM(D4:D31) -> -1511586.8

Sheet Для ПД
D1: 1 | J1: 2 | P1: 3 | V1: 4
D2: Январь | F2: Февраль | H2: Март | J2: Апрель | L2: Май | N2: Июнь | P2: Июль | R2: Август | T2: Сентябрь | V2: Октябрь | X2: Ноябрь | Z2: Декабрь | AB2: ИТОГО
B3: бюджет 2026 | C3: Ответсвенный | D3: План | E3: Факт | F3: План | G3: Факт | H3: План | I3: Факт | J3: План | K3: Факт | L3: План | M3: Факт | N3: План | O3: Факт | P3: План | Q3: Факт | R3: План | S3: Факт | T3: План | U3: Факт | V3: План | W3: Факт | X3: План | Y3: Факт | Z3: План | AA3: Факт | AB3: План | AC3: Факт
A4: Выручка от продаж разработки | B4: 47315721 | C4: Макшанова Л.М. | AB4: =B4 -> 47315721 | AC4: =E4+G4+I4+K4+M4+O4+Q4+S4+U4+W4+Y4+AA4 -> 0
A5: Выручка сервера | B5: 400000 | C5: Макшанова Л.М. | AB5: =B5 -> 400000 | AC5: =E5+G5+I5+K5+M5+O5+Q5+S5+U5+W5+Y5+AA5 -> 0
A6: Выручка коробки | B6: 2500000 | C6: Макшанова Л.М. | AB6: =B6 -> 2500000 | AC6: =E6+G6+I6+K6+M6+O6+Q6+S6+U6+W6+Y6+AA6 -> 0
A7: Выручка поддержка | B7: 3500000 | C7: Макшанова Л.М. | AB7: =B7 -> 3500000 | AC7: =E7+G7+I7+K7+M7+O7+Q7+S7+U7+W7+Y7+AA7 -> 0
A8: Выручка продукты | B8: 3000000 | C8: Макшанова Л.М. | AB8: =B8 -> 3000000 | AC8: =E8+G8+I8+K8+M8+O8+Q8+S8+U8+W8+Y8+AA8 -> 0
A9: Себестоимость от продаж | B9: 16739095 | C9: Сысоев В.С. | AB9: =B9 -> 16739095 | AC9: =E9+G9+I9+K9+M9+O9+Q9+S9+U9+W9+Y9+AA9 -> 0
A10: Себестоимость коробки | B10: 1250000 | C10: Макшанова Л.М. | AB10: =B10 -> 1250000 | AC10: =E10+G10+I10+K10+M10+O10+Q10+S10+U10+W10+Y10+AA10 -> 0
A11: Простой | B11: 1000000 | C11: Сысоев В.С. | AB11: =B11 -> 1000000 | AC11: =E11+G11+I11+K11+M11+O11+Q11+S11+U11+W11+Y11+AA11 -> 0
A12: Оплата попадосов | B12: 500000 | C12: Сысоев В.С. | AB12: =B12 -> 500000 | AC12: =E12+G12+I12+K12+M12+O12+Q12+S12+U12+W12+Y12+AA12 -> 0
A13: Выплата заработной платы разработка | B13: 3000000 | C13: Сысоев В.С. | AB13: =B13 -> 3000000 | AC13: =E13+G13+I13+K13+M13+O13+Q13+S13+U13+W13+Y13+AA13 -> 0
A14: Оплата аналитики | B14: 3000000 | C14: Сысоев В.С. | AB14: =B14 -> 3000000 | AC14: =E14+G14+I14+K14+M14+O14+Q14+S14+U14+W14+Y14+AA14 -> 0
A15: Откат ментам | B15: 4000000 | C15: Павлова Д.И. | AB15: =B15 -> 4000000 | AC15: =E15+G15+I15+K15+M15+O15+Q15+S15+U15+W15+Y15+AA15 -> 0
... A30: Налоги ЗП | B30: 3970100.5 | C30: Павлова Д.И. | AB30: =B30 -> 3970100.5 | AC30: =E30+G30+I30+K30+M30+O30+Q30+S30+U30+W30+Y30+AA30 -> 0
A34: 01.1.Выручка от продаж разработки | B34: 47315721
A35: 01.2.Выручка от продаж разработки
A36: 02.1.Выручка сервера | B36: 400000
A37: 02.2.Выручка сервера
A38: 03.1.Выручка коробки | B38: 2500000
A39: 03.2.Выручка коробки
A40: 04.1.Выручка поддержка | B40: 3500000
A41: 04.2.Выручка поддержка
A42: 05.1.Выручка продукты | B42: 3000000
A43: 05.2.Выручка продукты
A44: 06.Себестоимость от продаж | B44: 16739095
A45: 07.Себестоимость коробки | B45: 1250000
A46: 08.Простой | B46: 1000000
A47: 09.Оплата попадосов | B47: 500000
A48: 10.Выплата заработной платы разработка | B48: 3000000
A49: 11.Оплата аналитики | B49: 3000000
A50: 12.Откат ментам | B50: 4000000
A51: 13.Бонус отдела продаж | B51: 400000
A52: 14.Выплата заработной платы(Операционные) | B52: 1872000
A53: 15.Выплата заработной платы(Развитие) | B53: 3840000
A54: 16.Маркетинг | B54: 1000000
A55: 17.RND | B55: 1000000
... A65: 26.Налоги ЗП | B65: 3970100.5
A67: ЗП | B67: мес | C67: официальные | D67: самозанятые | E67: Нал | F67: налог зп
A68: =SUM('Помесячно Заполнить ответственн'!E7,'Помесячно Заполнить ответственн'!E9,'Помесячно Заполнить ответственн'!E10,'Помесячно Заполнить ответственн'!E11,'Помесячно Заполнить ответственн'!E12,'Помесячно Заполнить ответственн'!E14,'Помесячно Заполнить ответственн'!E15,'Помесячно Заполнить ответственн'!E16,'Помесячно Заполнить ответственн'!E25) -> -927533.33 | B68: я | C68: 1100000 | D68: 621980 | E68: =(A68+C68+D68)*(-1) -> -794446.67 | F68: =A68/100*30 -> -278260
A69: =SUM('Помесячно Заполнить ответственн'!E35,'Помесячно Заполнить ответственн'!E37,'Помесячно Заполнить ответственн'!E38,'Помесячно Заполнить ответственн'!E39,'Помесячно Заполнить ответственн'!E40,'Помесячно Заполнить ответственн'!E42,'Помесячно Заполнить ответственн'!E43,'Помесячно Заполнить ответственн'!E44,'Помесячно Заполнить ответственн'!E53) -> -1150646.7 | B69: ф | C69: 1100000 | D69: 1136000 | E69: =(A69+C69+D69)*(-1) -> -1085353.3 | F69: =A69/100*30 -> -345194
A70: =SUM('Помесячно Заполнить ответственн'!E63,'Помесячно Заполнить ответственн'!E65,'Помесячно Заполнить ответственн'!E66,'Помесячно Заполнить ответственн'!E67,'Помесячно Заполнить ответственн'!E68,'Помесячно Заполнить ответственн'!E70,'Помесячно Заполнить ответственн'!E71,'Помесячно Заполнить ответственн'!E72,'Помесячно Заполнить ответственн'!E81) -> -2542747 | B70: м | C70: 1100000 | D70: 1306500 | E70: =(A70+C70+D70)*(-1) -> 136247.05 | F70: =A70/100*30 -> -762824.11
A71: =sum('Помесячно Заполнить ответственн'!E91,'Помесячно Заполнить ответственн'!E93,'Помесячно Заполнить ответственн'!E94,'Помесячно Заполнить ответственн'!E95,'Помесячно Заполнить ответственн'!E96,'Помесячно Заполнить ответственн'!E98,'Помесячно Заполнить ответственн'!E99,'Помесячно Заполнить ответственн'!E100,'Помесячно Заполнить ответственн'!E109) -> -2520563.3 | B71: а | C71: 1100000 | D71: 1306500 | E71: =(A71+C71+D71)*(-1) -> 114063.33 | F71: =A71/100*30 -> -756169
A72: =Sum('Помесячно Заполнить ответственн'!E119,'Помесячно Заполнить ответственн'!E121,'Помесячно Заполнить ответственн'!E122,'Помесячно Заполнить ответственн'!E123,'Помесячно Заполнить ответственн'!E124,'Помесячно Заполнить ответственн'!E126,'Помесячно Заполнить ответственн'!E127,'Помесячно Заполнить ответственн'!E128,'Помесячно Заполнить ответственн'!E137) -> -2531833.3 | B72: м | C72: 1100000 | D72: =(A72+C72)*(-1) -> 1431833.3 | F72: =A72/100*30 -> -759550
A73: =SUM('Помесячно Заполнить ответственн'!E147,'Помесячно Заполнить ответственн'!E149,'Помесячно Заполнить ответственн'!E150,'Помесячно Заполнить ответственн'!E151,'Помесячно Заполнить ответственн'!E152,'Помесячно Заполнить ответственн'!E154,'Помесячно Заполнить ответственн'!E155,'Помесячно Заполнить ответственн'!E156,'Помесячно Заполнить ответственн'!E165) -> -3355347.6 | B73: и | C73: 1100000 | D73: 1306500 | E73: =(A73+C73+D73)*(-1) -> 948847.62 | F73: =A73/100*30 -> -1006604.3
A74: =SUM('Помесячно Заполнить ответственн'!E175,'Помесячно Заполнить ответственн'!E177,'Помесячно Заполнить ответственн'!E178,'Помесячно Заполнить ответственн'!E179,'Помесячно Заполнить ответственн'!E180,'Помесячно Заполнить ответственн'!E182,'Помесячно Заполнить ответственн'!E183,'Помесячно Заполнить ответственн'!E184,'Помесячно Заполнить ответственн'!E193) -> -2550984.8 | B74: и | C74: 1100000 | D74: 1306500 | E74: =(A74+C74+D74)*(-1) -> 144484.76 | F74: =A74/100*30 -> -765295.43
A75: =SUM('Помесячно Заполнить ответственн'!E203,'Помесячно Заполнить ответственн'!E205,'Помесячно Заполнить ответственн'!E206,'Помесячно Заполнить ответственн'!E207,'Помесячно Заполнить ответственн'!E208,'Помесячно Заполнить ответственн'!E210,'Помесячно Заполнить ответственн'!E211,'Помесячно Заполнить ответственн'!E212,'Помесячно Заполнить ответственн'!E221) -> -2576876.5 | B75: а | C75: 1100000 | D75: 1306500 | E75: =(A75+C75+D75)*(-1) -> 170376.49 | F75: =A75/100*30 -> -773062.95
A76: =SUM('Помесячно Заполнить ответственн'!E231,'Помесячно Заполнить ответственн'!E233,'Помесячно Заполнить ответственн'!E234,'Помесячно Заполнить ответственн'!E235,'Помесячно Заполнить ответственн'!E236,'Помесячно Заполнить ответственн'!E238,'Помесячно Заполнить ответственн'!E239,'Помесячно Заполнить ответственн'!E240,'Помесячно Заполнить ответственн'!E249) -> -2812976.5 | B76: с | C76: 1100000 | D76: 1306500 | E76: =(A76+C76+D76)*(-1) -> 406476.49 | F76: =A76/100*30 -> -843892.95
A77: =sum('Помесячно Заполнить ответственн'!E259,'Помесячно Заполнить ответственн'!E261,'Помесячно Заполнить ответственн'!E262,'Помесячно Заполнить ответственн'!E263,'Помесячно Заполнить ответственн'!E264,'Помесячно Заполнить ответственн'!E266,'Помесячно Заполнить ответственн'!E267,'Помесячно Заполнить ответственн'!E268,'Помесячно Заполнить ответственн'!E277) -> -2937158.1 | B77: о | C77: 1100000 | D77: 1306500 | E77: =(A77+C77+D77)*(-1) -> 530658.07 | F77: =A77/100*30 -> -881147.42
A78: =sum('Помесячно Заполнить ответственн'!E287,'Помесячно Заполнить ответственн'!E289,'Помесячно Заполнить ответственн'!E290,'Помесячно Заполнить ответственн'!E291,'Помесячно Заполнить ответственн'!E292,'Помесячно Заполнить ответственн'!E294,'Помесячно Заполнить ответственн'!E295,'Помесячно Заполнить ответственн'!E296,'Помесячно Заполнить ответственн'!E305) -> -3105414.9 | B78: н | C78: 1100000 | D78: 1306500 | E78: =(A78+C78+D78)*(-1) -> 698914.91 | F78: =A78/100*30 -> -931624.47
A79: =sum('Помесячно Заполнить ответственн'!E315,'Помесячно Заполнить ответственн'!E317,'Помесячно Заполнить ответственн'!E318,'Помесячно Заполнить ответственн'!E319,'Помесячно Заполнить ответственн'!E320,'Помесячно Заполнить ответственн'!E322,'Помесячно Заполнить ответственн'!E323,'Помесячно Заполнить ответственн'!E324,'Помесячно Заполнить ответственн'!E333) -> -3303644.9 | B79: д | C79: 1100000 | D79: 1306500 | E79: =(A79+C79+D79)*(-1) -> 897144.91 | F79: =A79/100*30 -> -991093.47
A80: =SUM(A68:A79) -> -30315727 | C80: =SUM(C68:C79) -> 13200000 | D80: =SUM(D68:D79) -> 14948313 | E80: =SUM(E68:E79) -> 2167413.6
A83: Официальные сотрудники | B83: оклад на руки | C83: Налог с оклада | E83: Самозанятые | F83: ЗП | H83: комиссии
A84: Агеев | B84: 150000 | C84: =B84*0.3 -> 45000 | E84: Виктория | F84: 45000 | H84: альфа ВС | I84: 254480 | J84: за вывод 10млн + мелоч
A85: Гатих | B85: 80000 | C85: =B85*0.3 -> 24000 | E85: Клишев | F85: 220000 | H85: Модуль ПД | I85: 169000 | J85: за вывод 10млн + мелоч
A86: Голубев | B86: 190000 | C86: =B86*0.3 -> 57000 | E86: Фильчуков | F86: 20000 | H86: Модуль ВС (500 переводы в месяц) | I86: 73080 | J86: ЕЖЕМЕСЯЧНО ПО 4900+990 БЕЛЫЙ БИЗНЕС+200 БЕЗОПАСНОСТЬ СЧЕТА
A87: Аналитик | B87: 150000 | C87: =B87*0.3 -> 45000 | H87: Модуль АИ
A88: Комаров | B88: 80000 | C88: =B88*0.3 -> 24000
A89: Ральченко | B89: 80000 | C89: =B89*0.3 -> 24000
A90: Абросимова | B90: 60000 | C90: =B90*0.3 -> 18000 | E90: Налоги
A91: Львов | B91: 100000 | C91: =B91*0.3 -> 30000 | E91: УСН | F91: =(B101-B102-F92)*0.15 -> 3174900.9
A92: Макшанова | B92: 120000 | C92: =B92*0.3 -> 36000 | E92: НДС | F92: =B101-(B101/1.05) -> 2465716
A93: Никешин | B93: 121700 | C93: =B93*0.3 -> 36510 | E93: ИП ПД | F93: 100000
A94: Федоров | B94: 159500 | C94: =B94*0.3 -> 47850 | E94: ИП ВС | F94: 100000
B95: 1291200 | C95: =SUM(C84:C94) -> 387360 | E95: Самозанятый Клишев | F95: 158400
A98: средняя | B98: =B95/11 -> 117381.82
A100: Максимаотный ФОТ официальный | B100: 1100000 | C100: =B100*0.3 -> 330000
A101: выручка | B101: =SUM('Поквартально'!J4:J9) -> 51780035
A102: ЗП | B102: =C80+D80 -> 28148313
